Workbook

Sheet CURSOS
G4: PROGRAMACIÓN DE CURSOS PRIMER SEMESTRE DEL 2026
G6: ESCUELA DE ADMINISTRACIÓN
M9: EXAMENES | P9: PRUEBA RECUPERATIVA
M10: 30 de junio al 10 de julio | P10: 30 de junio al 10 de julio
B11: CURSOS MINIMOS LICENCIATURA
H12: Clases | I12: Ayudantía | K12: Pruebas | M12: Examen | P12: Prueba Recuperativa
B13: Sigla | C13: Sec. | D13: Créd | E13: Nombre del curso | F13: Prof | G13: Requisitos | H13: Horario | I13: Horario | K13: Día/Módulo | M13: Día | N13: Hora | P13: Día | Q13: Hora
B14: EAA1110 | C14: 1 | D14: 10 | E14: COMPORTAMIENTO ORGANIZACIONAL | F14: G. MUÑOZ | G14: ADMISIÓN | H14: M-J:2 | I14: V:6 | K14: 29/abr:7 y 29/may:7 | M14: 45476 | N14: 8:20 - 10:20 | P14: 45476 | Q14: 0.72916667
B15: EAA1110 | C15: 2 | D15: 10 | E15: COMPORTAMIENTO ORGANIZACIONAL | F15: S. VALENZUELA | G15: ADMISIÓN | H15: M-J:4 | I15: V:6 | K15: 29/abr:7 y 29/may:7 | M15: 45476 | N15: 8:20 - 10:20 | P15: 45476 | Q15: 0.72916667
B16: EAA1110 | C16: 3 | D16: 10 | E16: COMPORTAMIENTO ORGANIZACIONAL | F16: M.E. VIGNEAUX | G16: ADMISIÓN | H16: M-J:4 | I16: V:6 | K16: 29/abr:7 y 29/may:7 | M16: 45476 | N16: 8:20 - 10:20 | P16: 45476 | Q16: 0.72916667
B17: EAA1110 | C17: 4 | D17: 10 | E17: COMPORTAMIENTO ORGANIZACIONAL | F17: E. KAUSEL | G17: ADMISIÓN | H17: L-W:3 | I17: V:6 | K17: 29/abr:7 y 29/may:7 | M17: 45476 | N17: 8:20 - 10:20 | P17: 45476 | Q17: 0.72916667
B18: EAA1110 | C18: 5 | D18: 10 | E18: COMPORTAMIENTO ORGANIZACIONAL | F18: S. VALENZUELA | G18: ADMISIÓN | H18: M-J:5 | I18: V:6 | K18: 29/abr:7 y 29/may:7 | M18: 45476 | N18: 8:20 - 10:20 | P18: 45476 | Q18: 0.72916667
B19: EAA1110 | C19: 6 | D19: 10 | E19: COMPORTAMIENTO ORGANIZACIONAL | F19: G. MUÑOZ | G19: ADMISIÓN | H19: M-J:3 | I19: V:6 | K19: 29/abr:7 y 29/may:7 | M19: 45476 | N19: 8:20 - 10:20 | P19: 45476 | Q19: 0.72916667
B20: EAA1110 | C20: 7 | D20: 10 | E20: COMPORTAMIENTO ORGANIZACIONAL | F20: F. VALDOVINOS | G20: ADMISIÓN | H20: M-J:1 | I20: V:6 | K20: 29/abr:7 y 29/may:7 | M20: 45476 | N20: 8:20 - 10:20 | P20: 45476 | Q20: 0.72916667
B21: EAA1110 | C21: 8 | D21: 10 | E21: COMPORTAMIENTO ORGANIZACIONAL | F21: M.E. VIGNEAUX | G21: ADMISIÓN | H21: M-J:3 | I21: V:6 | K21: 29/abr:7 y 29/may:7 | M21: 45476 | N21: 8:20 - 10:20 | P21: 45476 | Q21: 0.72916667
B22: EAA1210 | C22: 1 | D22: 10 | E22: CONTABILIDAD | F22: J. GÁLVEZ | G22: ADMISIÓN | H22: M-J:3 | I22: V:3/L:7 | K22: 13/abr:7 y 26/may:7 | M22: 45847 | N22: 8:20 - 10:20 | P22: 45847 | Q22: 0.72916667
B23: EAA1210 | C23: 2 | D23: 10 | E23: CONTABILIDAD | F23: H. GODOY | G23: ADMISIÓN | H23: L-W:1 | I23: V:3/L:7 | K23: 13/abr:7 y 26/may:7 | M23: 45847 | N23: 8:20 - 10:20 | P23: 45847 | Q23: 0.72916667
B24: EAA1210 | C24: 3 | D24: 10 | E24: CONTABILIDAD | F24: R. GANA | G24: ADMISIÓN | H24: L-W:3 | I24: V:3/L:7 | K24: 13/abr:7 y 26/may:7 | M24: 45847 | N24: 8:20 - 10:20 | P24: 45847 | Q24: 0.72916667
B25: EAA1210 | C25: 4 | D25: 10 | E25: CONTABILIDAD | F25: J. GÁLVEZ | G25: ADMISIÓN | H25: M-J:4 | I25: V:3/L:7 | K25: 13/abr:7 y 26/may:7 | M25: 45847 | N25: 8:20 - 10:20 | P25: 45847 | Q25: 0.72916667
... B42: EAA2210 | C42: 1 | D42: 10 | E42: TEORÍA FINANCIERA | F42: D. BUCHUK | G42: Admisión 2020 - 2023: EAA2410-EAA1520-IIC1103 Y EAE2110 CON | H42: L-W:3 | I42: V:6 | K42: 14/abr:7 y 1/jun:7 | M42: 45847 | N42: 13:30 - 15:30 | P42: 45847 | Q42: 0.72916667
G43: Admisión 2024 y posteriores: EAA2410-EAA1520-IIC1103 CON Y EAE2110 CON
B44: EAA2210 | C44: 2 | D44: 10 | E44: TEORÍA FINANCIERA | F44: D. BUCHUK | G44: Admisión 2020 - 2023: EAA2410-EAA1520-IIC1103 Y EAE2110 CON | H44: L-W:4 | I44: V:6 | K44: 14/abr:7 y 1/jun:7 | M44: 45847 | N44: 13:30 - 15:30 | P44: 45847 | Q44: 0.72916667
G45: Admisión 2024 y posteriores: EAA2410-EAA1520-IIC1103 CON Y EAE2110 CON
B46: EAA2210 | C46: 3 | D46: 10 | E46: TEORÍA FINANCIERA | F46: M. VALENZUELA | G46: Admisión 2020 - 2023: EAA2410-EAA1520-IIC1103 Y EAE2110 CON | H46: M-J:1 | I46: V:6 | K46: 14/abr:7 y 1/jun:7 | M46: 45847 | N46: 13:30 - 15:30 | P46: 45847 | Q46: 0.72916667
G47: Admisión 2024 y posteriores: EAA2410-EAA1520-IIC1103 CON Y EAE2110 CON
B48: EAA2210 | C48: 4 | D48: 10 | E48: TEORÍA FINANCIERA | F48: C. SILVA | G48: Admisión 2020 - 2023: EAA2410-EAA1520-IIC1103 Y EAE2110 CON | H48: M-J:6 | I48: V:6 | K48: 14/abr:7 y 1/jun:7 | M48: 45847 | N48: 13:30 - 15:30 | P48: 45847 | Q48: 0.72916667
G49: Admisión 2024 y posteriores: EAA2410-EAA1520-IIC1103 CON Y EAE2110 CON
B50: EAA2220 | C50: 1 | D50: 10 | E50: COSTOS | F50: G. MATURANA | G50: EAA2410 | H50: W:2 | I50: V:2 | K50: 10/abr:7 y 15/may:7 | M50: 45475 | N50: 8:20 - 10:20 | P50: 45475 | Q50: 0.72916667
B51: EAA2220 | C51: 2 | D51: 10 | E51: COSTOS | F51: G. MATURANA | G51: EAA2410 | H51: W:3 | I51: V:2 | K51: 10/abr:7 y 15/may:7 | M51: 45475 | N51: 8:20 - 10:20 | P51: 45475 | Q51: 0.72916667
B52: EAA2220 | C52: 3 | D52: 10 | E52: COSTOS | F52: M. DEL SANTE | G52: EAA2410 | H52: M:3 | I52: V:2 | K52: 10/abr:7 y 15/may:7 | M52: 45475 | N52: 8:20 - 10:20 | P52: 45475 | Q52: 0.72916667
B53: EAA2220 | C53: 4 | D53: 10 | E53: COSTOS | F53: M. DEL SANTE | G53: EAA2410 | H53: M:4 | I53: V:2 | K53: 10/abr:7 y 15/may:7 | M53: 45475 | N53: 8:20 - 10:20 | P53: 45475 | Q53: 0.72916667
B54: EAA223A | C54: 1 | D54: 10 | E54: CONTABILIDAD GERENCIAL | F54: I. RODRÍGUEZ | G54: EAA218A y EAA220B | H54: M-J:3 | I54: V:6 | K54: 14/abr:7 y 1/jun:7 | M54: 45847 | N54: 8:20 - 10:20 | P54: 45847 | Q54: 0.72916667
B55: EAA223A | C55: 2 | D55: 10 | E55: CONTABILIDAD GERENCIAL | F55: M. DEL SANTE | G55: EAA218A y EAA220B | H55: L-W:2 | I55: V:6 | K55: 14/abr:7 y 1/jun:7 | M55: 45847 | N55: 8:20 - 10:20 | P55: 45847 | Q55: 0.72916667
B56: EAA223A | C56: 3 | D56: 10 | E56: CONTABILIDAD GERENCIAL | F56: M. DEL SANTE | G56: EAA218A y EAA220B | H56: L-W:4 | I56: V:6 | K56: 14/abr:7 y 1/jun:7 | M56: 45847 | N56: 8:20 - 10:20 | P56: 45847 | Q56: 0.72916667
B57: EAA223A | C57: 4 | D57: 10 | E57: CONTABILIDAD GERENCIAL | F57: L.CAMILLA | G57: EAA218A y EAA220B | H57: L-W:1 | I57: V:6 | K57: 14/abr:7 y 1/jun:7 | M57: 45847 | N57: 8:20 - 10:20 | P57: 45847 | Q57: 0.72916667
B58: EAA2240 | C58: 1 | D58: 10 | E58: CONTABILIDAD GERENCIAL | F58: I. RODRÍGUEZ | G58: EAA2210 y EAA2220 | H58: M-J:3 | I58: V:6 | K58: 14/abr:7 y 1/jun:7 | M58: 45847 | N58: 8:20 - 10:20 | P58: 45847 | Q58: 0.72916667
B59: EAA2240 | C59: 2 | D59: 10 | E59: CONTABILIDAD GERENCIAL | F59: M. DEL SANTE | G59: EAA2210 y EAA2220 | H59: L-W:2 | I59: V:6 | K59: 14/abr:7 y 1/jun:7 | M59: 45847 | N59: 8:20 - 10:20 | P59: 45847 | Q59: 0.72916667
B60: EAA2240 | C60: 3 | D60: 10 | E60: CONTABILIDAD GERENCIAL | F60: M. DEL SANTE | G60: EAA2210 y EAA2220 | H60: L-W:4 | I60: V:6 | K60: 14/abr:7 y 1/jun:7 | M60: 45847 | N60: 8:20 - 10:20 | P60: 45847 | Q60: 0.72916667
B61: EAA2240 | C61: 4 | D61: 10 | E61: CONTABILIDAD GERENCIAL | F61: L.CAMILLA | G61: EAA2210 y EAA2220 | H61: L-W:1 | I61: V:6 | K61: 14/abr:7 y 1/jun:7 | M61: 45847 | N61: 8:20 - 10:20 | P61: 45847 | Q61: 0.72916667
... B92: EAA1520 | C92: 5 | D92: 10 | E92: INFERENCIA ESTADÍSTICA | F92: R. ARAVENA | G92: EAA1510 | H92: M-J:2 | I92: L:6 - L:3 | K92: 27/abr:7 y 5/jun:7 | M92: 45481 | N92: 8:20 - 10:20 | P92: 45481 | Q92: 0.72916667
B94: TALLERES DE COMPUTACIÓN
H95: Examen de Suficiencia
B96: Sigla | C96: Sec. | D96: Créd | E96: Nombre del curso | F96: Prof | G96: Requisitos | H96: Día/Hora
B97: EAA162C | C97: 1 | D97: 0 | E97: TALLER DE COMPUTACIÓN I (EXCEL) | F97: A. CANALES | G97: ADMISION | H97: 25/marzo: 17:30 - 19:30 horas
B98: EAA163C | C98: 1 | D98: 0 | E98: TALLER DE COMPUTACIÓN II (ACCES) | F98: S.FUSTER | G98: ADMISION | H98: 26/marzo: 17:30 - 19:30 horas
B101: CURSOS NIVEL 200 OPTATIVOS LICENCIATURA
B102: Estudiantes de admisión 2010 a 2019 deben tomar 20 créditos de cursos optativos 200 de la Escuela de Administración
B103: Estudiantes admisión 2020 y posteriores deben tomar los cursos que son parte de un minor o forman parte del listado de cursos optativos reconocidos en ese currículo
H105: Clases | I105: Ayudantía | K105: Pruebas | M105: Examen | P105: Prueba Recuperativa
B106: Sigla | C106: Sec. | D106: Créd | E106: Nombre del curso | F106: Prof | G106: Requisitos | H106: Horario | I106: Horario | K106: Día/Módulo | M106: Día | N106: Hora | P106: Día | Q106: Hora
B107: EAA200E | C107: 1 | D107: 10 | E107: DECISIONES DIFÍCILES 3, 5 | F107: C. PORTALES | G107: EAE2110 | H107: L-W:4 | I107: W:6 | K107: PF | M107: 45841 | N107: 13:30 - 15:30 | P107: PF | Q107: PF
B108: EAA2018 | C108: 1 | D108: 10 | E108: ESTRATEGIAS COMPETITIVAS EN PLATAFORMAS DIGITALES 3 | F108: G. SARAIVA | G108: EAF2010 y EAA2410 y EAE2510 | H108: M-J:1 | I108: W:5 | K108: 9/abr: 1 y 28/may:1 | M108: 45846 | N108: 12:20 - 14:20 | P108: PF | Q108: PF
B109: EAA2072 | C109: 1 | D109: 5 | E109: INNOVACIÓN Y TECNOLOGÍAS EMERGENTES 3 | F109: N. MONCADA | G109: EAA208E o (EAA2310 y EAA2410) | H109: L:2 | I109: W:2 | K109: PF | M109: PF | N109: PF | P109: PF | Q109: PF
B110: EAA2075 | C110: 1 | D110: 5 | E110: FINANCIAMIENTO DE STARUPS 3 | F110: Y. SCHKOLNICK | G110: EAA2210 | H110: W:4 | I110: W:7 | K110: 29/abr:4 | M110: 45832 | N110: 17:30 - 19:30 | P110: PF | Q110: PF
B111: EAA2079 | C111: 1 | D111: 5 | E111: METODOLOGÍAS ÁGILES PARA LA INNOVACIÓN ORGANIZACIONAL 3 | F111: M.J. FERNÁNDEZ | G111: EAA2410 y EAA2310 | H111: J:6-7 | I111: M:7 | K111: 7/may:6-7 | M111: PF | N111: PF | P111: PF | Q111: PF
B112: EAA2080 | C112: 1 | D112: 10 | E112: INNOVACIÓN SISTÉMICA Y ECOSISTEMAS DE EMPRENDIMIENTO 3 | F112: N. MONCADA | G112: EAA208E o (EAA2410 o EAA200B o EAA200A) y (EAA2310 o EAA230A) | H112: L-W:3 | I112: J:4 | K112: 15/abr:3 y 15/jun:3 | M112: PF | N112: PF | P112: PF | Q112: PF
B113: EAA2081 | C113: 1 | D113: 5 | E113: GESTIÓN DE LA INNOVACIÓN 3 | F113: J.M. CHAPA | G113: EAA208E o (EAA2410 y EAA2310) o (EAA200B y EAA230A) | H113: W:1 | I113: L:1 | K113: PF | M113: PF | N113: PF | P113: PF | Q113: PF
B114: EAA2091 | C114: 1 | D114: 10 | E114: FUNDAMENTOS DE LA TEORÍA PRÁCTICA DE LA INNOVACIÓN 3 | F114: P. BROITMAN | G114: EAA208E o (EAA2410 y EAA2310) o (EAA200B y EAA230A) | H114: M-J:2 | I114: -- | K114: 8/abr:7 y 2/jun:7 | M114: 45838 | N114: 8:20 - 10:20 | P114: PF | Q114: PF
B115: EAA2091 | C115: 2 | D115: 10 | E115: FUNDAMENTOS DE LA TEORÍA PRÁCTICA DE LA INNOVACIÓN 3 | F115: M. VILLALOBOS | G115: EAA208E o (EAA2410 y EAA2310) o (EAA200B y EAA230A) | H115: L-W:1 | I115: -- | K115: 8/abr:7 y 2/jun:7 | M115: 45838 | N115: 8:20 - 10:20 | P115: PF | Q115: PF
B116: EAA209L | C116: 1 | D116: 10 | E116: DESIGN THINKING PARA NEGOCIOS 3 | F116: J.M. CHAPA | G116: EAA2410 ó EAA200B ó EAA201E | H116: M-J:1 | I116: -- | K116: PF | M116: PF | N116: PF | P116: PF | Q116: PF
B117: EAA209L | C117: 2 | D117: 10 | E117: DESIGN THINKING PARA NEGOCIOS 3 (INGLÉS) | F117: P. BROITMAN | G117: EAA2410 ó EAA200B ó EAA201E | H117: M-J:3 | I117: -- | K117: 16/abr: 3 y 4/jun:3 | M117: PF | N117: PF | P117: PF | Q117: PF
B118: EAA222F | C118: 1 | D118: 10 | E118: MERCADO DE CAPITALES 2 | F118: A. KAPLAN | G118: EAA213A Ó EAA1220 | H118: L:5-6 | I118: -- | K118: 20/abr:5-6 y 8/jun:5-6 | M118: 45838 | N118: 12:20 - 14:20 | P118: PF | Q118: PF
B119: EAA2225 | C119: 1 | D119: 10 | E119: FINANZAS INTERNACIONALES 2 | F119: C. BURGA | G119: EAA2210 | H119: L-W:4 | I119: J:1 | K119: 4/may:4 | M119: 45841 | N119: 13:30 - 15:30 | P119: PF | Q119: PF
B120: EAA224A | C120: 1 | D120: 10 | E120: SEMINARIO DE FINANZAS: FINANCIAMIENTO EMPRESARIAL 2 | F120: R. MUÑOZ | G120: (EAA213 ó EAA1220) y (EAE2210 0 EAE220D) | H120: L:2-3 | I120: W:2 | K120: 29/abr:2 | M120: 45839 | N120: 13:30 - 15:30 | P120: PF | Q120: PF
B121: EAA2245 | C121: 1 | D121: 10 | E121: INVERSIONES DE RENTA FIJA 2 | F121: D. BUCHUK | G121: EAA2210 ó (EAA220B o EAA220A) | H121: M-J:3 | I121: J:5 | K121: 16/abr:5 | M121: 45845 | N121: 13:30 - 15:30 | P121: PF | Q121: PF
B122: EAA2260 | C122: 1 | D122: 10 | E122: VALORACIÓN FINANCIERA DE EMPRESAS 2 | F122: M. ERRÁZURIZ / M. ERRÁZURIZ | G122: EAA2210 ó (EAA220B o EAA220A) | H122: L:7-8 | I122: -- | K122: PF | M122: PF | N122: PF | P122: PF | Q122: PF
B123: EAA284A | C123: 1 | D123: 10 | E123: DERECHO DE LA EMPRESA 3 | F123: K. MOORE | G123: EAA2230 ó EAA218A ó EAA210E | H123: M-J:3 | I123: -- | K123: 16/abr:3 y 16/jun:3 | M123: PF | N123: PF | P123: PF | Q123: PF
B124: EAA2841 | C124: 1 | D124: 10 | E124: SOCIEDAD CIVIL Y FILANTROPIA 3, 4, 5 | F124: A. HOLZAPFEL/P. STREETER | G124: EAA2230 o EAA218A o EAA200B | H124: M:5-6 | I124: J:5 | K124: 12/may:5-6 | M124: 45848 | N124: 13:30 - 15:30 | P124: PF | Q124: PF
B125: EAA296A | C125: 1 | D125: 10 | E125: ESTUDIOS EN ADMINISTRACIÓN DE EMPRESAS I | F125: J. GÁLVEZ | G125: EAE250A-UA05-AUTORIZACION DIRECCION | H125: PF | I125: -- | K125: PF | M125: PF | N125: PF
B126: Minor: 1Políticas Públicas (PP) / 2Macroeconomía y Finanzas (MF) / 3Innovación (IN) / 4Sustentabilidad (S) / 5Persona y Sociedad (PS)
B129: CURSOS NIVEL 3000 MÍNIMOS INGENIERÍA COMERCIAL / MENCIÓN ADMINISTRACIÓN
H130: Clases | I130: Ayudantía | K130: Pruebas | M130: Examen | P130: Prueba Recuperativa
B131: Sigla | C131: Sec. | D131: Créd | E131: Nombre del curso | F131: Prof | G131: Requisitos | H131: Horario | I131: Horario | K131: Día/Módulo | M131: Día | N131: Hora | P131: Día | Q131: Hora
B132: EAA305A | C132: 1 | D132: 12 | E132: DIRECCIÓN DE EMPRESAS Y ESTRATEGIA | F132: J. RIVERA | G132: EAA223A(c) y EAA230A y EAA240A y EAA321B(c) | H132: L:5-6 | I132: V:1 | K132: 14abr:7 y 28/may:7 | M132: 45473 | N132: 13:30 - 15:30 | P132: 45473 | Q132: 0.72916667
B133: EAA305A | C133: 2 | D133: 12 | E133: DIRECCIÓN DE EMPRESAS Y ESTRATEGIA | F133: J. RIVERA | G133: EAA223A(c) y EAA230A y EAA240A y EAA321B(c) | H133: M:5-6 | I133: V:1 | K133: 14abr:7 y 28/may:7 | M133: 45473 | N133: 13:30 - 15:30 | P133: 45473 | Q133: 0.72916667
B134: EAA305A | C134: 3 | D134: 12 | E134: DIRECCIÓN DE EMPRESAS Y ESTRATEGIA | F134: J. TARZIJAN | G134: EAA223A(c) y EAA230A y EAA240A y EAA321B(c) | H134: L-W:4 | I134: V:1 | K134: 14abr:7 y 28/may:7 | M134: 45473 | N134: 13:30 - 15:30 | P134: 45473 | Q134: 0.72916667
B135: EAA305A | C135: 4 | D135: 12 | E135: DIRECCIÓN DE EMPRESAS Y ESTRATEGIA | F135: C. PORTALES | G135: EAA223A(c) y EAA230A y EAA240A y EAA321B(c) | H135: L-W:2 | I135: V:1 | K135: 14abr:7 y 28/may:7 | M135: 45473 | N135: 13:30 - 15:30 | P135: 45473 | Q135: 0.72916667
B136: EAA3401 | C136: 1 | D136: 10 | E136: DIRECCIÓN DE EMPRESAS Y ESTRATEGIA | F136: J. RIVERA | G136: EAA2110 y EAA2240 y EAA2320 y EAA3201(c) | H136: L:5-6 | I136: V:1 | K136: 14abr:7 y 28/may:7 | M136: 45473 | N136: 13:30 - 15:30 | P136: 45473 | Q136: 0.72916667
B137: EAA3401 | C137: 2 | D137: 10 | E137: DIRECCIÓN DE EMPRESAS Y ESTRATEGIA | F137: J. RIVERA | G137: EAA2110 y EAA2240 y EAA2320 y EAA3201(c) | H137: M:5-6 | I137: V:1 | K137: 14abr:7 y 28/may:7 | M137: 45473 | N137: 13:30 - 15:30 | P137: 45473 | Q137: 0.72916667
B138: EAA3401 | C138: 3 | D138: 10 | E138: DIRECCIÓN DE EMPRESAS Y ESTRATEGIA | F138: J. TARZIJAN | G138: EAA2110 y EAA2240 y EAA2320 y EAA3201(c) | H138: L-W:4 | I138: V:1 | K138: 14abr:7 y 28/may:7 | M138: 45473 | N138: 13:30 - 15:30 | P138: 45473 | Q138: 0.72916667
B139: EAA3401 | C139: 4 | D139: 10 | E139: DIRECCIÓN DE EMPRESAS Y ESTRATEGIA | F139: C. PORTALES | G139: EAA2110 y EAA2240 y EAA2320 y EAA3201(c) | H139: L-W:2 | I139: V:1 | K139: 14abr:7 y 28/may:7 | M139: 45473 | N139: 13:30 - 15:30 | P139: 45473 | Q139: 0.72916667
B140: EAA305E | C140: 1 | D140: 12 | E140: CREACIÓN DE NUEVAS EMPRESAS | F140: M.C. LECAROS | G140: EAA305A-EAA321B | H140: W:5-6 | I140: - | K140: 14abr:7 y 28/may:7 | M140: 45473 | N140: 13:30 - 15:30 | P140: 45473 | Q140: 0.72916667
B141: EAA305E | C141: 2 | D141: 12 | E141: CREACIÓN DE NUEVAS EMPRESAS | F141: Y. SCHKOLNICK | G141: EAA305A-EAA321B | H141: W:5-6 | I141: - | K141: 14abr:7 y 28/may:7 | M141: 45473 | N141: 13:30 - 15:30 | P141: 45473 | Q141: 0.72916667
B142: EAA305E | C142: 3 | D142: 12 | E142: CREACIÓN DE NUEVAS EMPRESAS | F142: N. MONCADA | G142: EAA305A-EAA321B | H142: W:5-6 | I142: - | K142: 14abr:7 y 28/may:7 | M142: 45473 | N142: 13:30 - 15:30 | P142: 45473 | Q142: 0.72916667
B143: EAA3601 | C143: 1 | D143: 10 | E143: CREACIÓN DE NUEVAS EMPRESAS | F143: M.C. LECAROS | G143: EAA3401-EAA3201 y EAA2420 | H143: W:5-6 | I143: - | K143: 14abr:7 y 28/may:7 | M143: 45473 | N143: 13:30 - 15:30 | P143: 45473 | Q143: 0.72916667
... B158: EAA3501 | C158: 3 | D158: 10 | E158: GESTIÓN DE OPERACIONES | F158: M. CEPEDA | G158: (EAA2420 y EAE2510) o (EAE2130 y EAE2510) | H158: J:5-6 | I158: V:4 | K158: 23/abr:7 y 10/jun:7 | M158: 45480 | N158: 8:20 - 10:20 | P158: 45480 | Q158: 0.72916667
B159: EAA3101 | C159: 1 | D159: 5 | E159: LIDERAZGO ESTRATÉGICO | F159: V. VÁSQUEZ | G159: (EAA2110 y EAA3401) o (EAA240A y EAA305A) | H159: L:3-4 | I159: - | K159: 14/may:7 | M159: PF | N159: PF | P159: 45806 | Q159: 0.72916667
B160: EAA3101 | C160: 2 | D160: 5 | E160: LIDERAZGO ESTRATÉGICO | F160: S. VALENZUELA | G160: (EAA2110 y EAA3401) o (EAA240A y EAA305A) | H160: M:2-3 | I160: - | K160: 14/may:7 | M160: PF | N160: PF | P160: 45806 | Q160: 0.72916667
B161: EAA3101 | C161: 3 | D161: 5 | E161: LIDERAZGO ESTRATÉGICO | F161: S. VALENZUELA | G161: (EAA2110 y EAA3401) o (EAA240A y EAA305A) | H161: J:2-3 | I161: - | K161: 14/may:7 | M161: PF | N161: PF | P161: 45806 | Q161: 0.72916667
B162: EAA3101 | C162: 4 | D162: 5 | E162: LIDERAZGO ESTRATÉGICO | F162: M.E. VIGNEAUX | G162: (EAA2110 y EAA3401) o (EAA240A y EAA305A) | H162: M:5-6 | I162: - | K162: 14/may:7 | M162: PF | N162: PF | P162: 45806 | Q162: 0.72916667
B163: EAA3500 | C163: 1 | D163: 15 | E163: PRÁCTICA PROFESIONAL | F163: PF | G163: EAF2500 y EAA3401 y EAA3201 y EAA2420 | H163: - | I163: - | K163: - | M163: - | N163: - | P163: - | Q163: -
B166: CURSOS NIVEL 3000 OPTATIVOS INGENIERÍA COMERCIAL / MENCIÓN ADMINISTRACIÓN
H167: Clases | I167: Ayudantía | K167: Pruebas | M167: Examen | P167: Prueba Recuperativa
B168: Sigla | C168: Sec. | D168: Créd | E168: Nombre del curso | F168: Prof | G168: Requisitos | H168: Horario | I168: Horario | K168: Día/Módulo | M168: Día | N168: Hora | P168: Día | Q168: Hora
B169: EAA3411 | C169: 1 | D169: 10 | E169: ESTRATEGIA COMPETITIVA APLICADA | F169: A. GONZÁLEZ | G169: (EAE2510 y EAA2420(c)) o (EAE2510 y EAE2130(c)) | H169: M-J:5 | I169: J:6 | K169: PF | M169: PF | N169: PF | P169: PF | Q169: PF
B170: EAA3112 | C170: 1 | D170: 10 | E170: LA PERSONA DEL LIDER | F170: V. VÁSQUEZ | G170: EAA3201 | H170: M:3-4 | I170: -- | K170: 21/abr:3-4 y 9/jun:3-4 | M170: PF | N170: PF | P170: PF | Q170: PF
B171: EAA317A | C171: 1 | D171: 12 | E171: LIDERAZGO ORIENTADO POR VALORES | F171: C. PAUL / T. KAPLAN | G171: EAF2500 | H171: M:1-2 | I171: V:5 | K171: PF | M171: 45831 | N171: 8:20 - 10:50 | P171: PF | Q171: PF
B172: EAA3119 | C172: 1 | D172: 10 | E172: INTELIGENCIA EMOCIONAL EN LA EMPRESA | F172: N. ABARCA | G172: EAA2110 | H172: W:2-3 | I172: L:3 | K172: PF | M172: 45832 | N172: 0.40277778 | P172: PF | Q172: PF
B173: EAA3210 | C173: 1 | D173: 12 | E173: TEORÍA DE INVERSIONES | F173: E. WALKER | G173: (EAA2240 ó EAA223A) y (EAE2510 ó EAE250A) | H173: M-J:4 | I173: L:4 | K173: 4/may:4 | M173: 45839 | N173: 13:30 - 15:30 | P173: PF | Q173: PF
B174: EAA3218 | C174: 1 | D174: 10 | E174: INVERSIÓN EN ACTIVOS ALTERNATIVOS | F174: R.MOGROVEJO | G174: (EAA3201(c) o EAA321B(c)) y (EAA2240 o EAA223A) | H174: W:1-2 | I174: J:1 | K174: PF | M174: PF | N174: PF | P174: PF | Q174: PF
...

Sheet VACANTES
F1: PONTIFICIA UNIVERSIDAD CATOLICA DE CHILE
F2: ESCUELA DE ADMINISTRACION
F3: PROGRAMACIÓN DE CURSOS SEGUNDO DEL 2006
B5: CURSOS MINIMOS LICENCIATURA
K6: =SUM(K8:K40)+SUM(K58:K67)+SUM(K72:K80)+SUM(K85:K93)+SUM(K97:K102)+SUM(K106:K133)+SUM(K138:K144)+SUM(K151:K178)+SUM(K185:K196)+SUM(K208:K209)+SUM(K216:K222) -> 501 | L6: =SUM(L8:L40)+SUM(L58:L67)+SUM(L72:L80)+SUM(L85:L93)+SUM(L97:L102)+SUM(L106:L133)+SUM(L138:L144)+SUM(L151:L178)+SUM(L185:L196)+SUM(L208:L209)+SUM(L216:L222) -> 305
A7: Sigla | B7: Sigla | C7: Sec. | D7: Créd | E7: Nombre del curso | F7: Prof | G7: Requisitos | H7: UA05 | I7: UA11 | J7: UA07 | K7: FG | L7: INTERC. | M7: Juan Edo. | N7: TOTAL | O7: Sala | P7: Nº alumnos/Sala
A8: =+#REF! -> #REF! | B8: =+#REF! -> #REF! | C8: =+#REF! -> #REF! | D8: =+#REF! -> #REF! | E8: =+#REF! -> #REF! | F8: =+#REF! -> #REF! | G8: =+#REF! -> #REF! | H8: 55 | K8: 5 | L8: 5 | N8: =SUM(H8:L8) -> 65 | O8: =+#REF! -> #REF! | P8: 80
A9: =+#REF! -> #REF! | B9: =+#REF! -> #REF! | C9: =+#REF! -> #REF! | D9: =+#REF! -> #REF! | E9: =+#REF! -> #REF! | F9: =+#REF! -> #REF! | G9: =+#REF! -> #REF! | H9: 55 | K9: 5 | L9: 5 | N9: =SUM(H9:L9) -> 65 | O9: =+#REF! -> #REF! | P9: 100
A10: =+#REF! -> #REF! | B10: =+#REF! -> #REF! | C10: =+#REF! -> #REF! | D10: =+#REF! -> #REF! | E10: =+#REF! -> #REF! | F10: =+#REF! -> #REF! | G10: =+#REF! -> #REF! | H10: 55 | K10: 5 | L10: 5 | N10: =SUM(H10:L10) -> 65 | O10: =+#REF! -> #REF! | P10: 80
A11: =+#REF! -> #REF! | B11: =+#REF! -> #REF! | C11: =+#REF! -> #REF! | D11: =+#REF! -> #REF! | E11: =+#REF! -> #REF! | F11: =+#REF! -> #REF! | G11: =+#REF! -> #REF! | H11: 55 | K11: 5 | L11: 5 | N11: =SUM(H11:L11) -> 65 | O11: =+#REF! -> #REF! | P11: 100
A12: =+#REF! -> #REF! | B12: =+#REF! -> #REF! | C12: =+#REF! -> #REF! | D12: =+#REF! -> #REF! | E12: =+#REF! -> #REF! | F12: =+#REF! -> #REF! | G12: =+#REF! -> #REF! | H12: 40 | J12: 15 | K12: 5 | L12: 3 | N12: =SUM(H12:L12) -> 63 | O12: =+#REF! -> #REF! | P12: 75
A13: =+#REF! -> #REF! | B13: =+#REF! -> #REF! | C13: =+#REF! -> #REF! | D13: =+#REF! -> #REF! | E13: =+#REF! -> #REF! | F13: =+#REF! -> #REF! | G13: =+#REF! -> #REF! | H13: 40 | J13: 15 | K13: 5 | L13: 3 | N13: =SUM(H13:L13) -> 63 | O13: =+#REF! -> #REF! | P13: 60
A14: =+#REF! -> #REF! | B14: =+#REF! -> #REF! | C14: =+#REF! -> #REF! | D14: =+#REF! -> #REF! | E14: =+#REF! -> #REF! | F14: =+#REF! -> #REF! | G14: =+#REF! -> #REF! | H14: 51 | J14: 14 | K14: 5 | N14: =SUM(H14:L14) -> 70 | O14: =+#REF! -> #REF! | P14: 120
A15: =+#REF! -> #REF! | B15: =+#REF! -> #REF! | C15: =+#REF! -> #REF! | D15: =+#REF! -> #REF! | E15: =+#REF! -> #REF! | F15: =+#REF! -> #REF! | G15: =+#REF! -> #REF! | H15: 51 | J15: 14 | K15: 5 | N15: =SUM(H15:L15) -> 70 | O15: =+#REF! -> #REF! | P15: 110
A16: =+#REF! -> #REF! | B16: =+#REF! -> #REF! | C16: =+#REF! -> #REF! | D16: =+#REF! -> #REF! | E16: =+#REF! -> #REF! | F16: =+#REF! -> #REF! | G16: =+#REF! -> #REF! | H16: 51 | J16: 14 | K16: 5 | N16: =SUM(H16:L16) -> 70 | O16: =+#REF! -> #REF! | P16: 80
A17: =+#REF! -> #REF! | B17: =+#REF! -> #REF! | C17: =+#REF! -> #REF! | D17: =+#REF! -> #REF! | E17: =+#REF! -> #REF! | F17: =+#REF! -> #REF! | G17: =+#REF! -> #REF! | H17: 51 | J17: 14 | K17: 5 | N17: =SUM(H17:L17) -> 70 | O17: =+#REF! -> #REF! | P17: 110
A18: =+#REF! -> #REF! | B18: =+#REF! -> #REF! | C18: =+#REF! -> #REF! | D18: =+#REF! -> #REF! | E18: =+#REF! -> #REF! | F18: =+#REF! -> #REF! | G18: =+#REF! -> #REF! | H18: 45 | K18: 5 | L18: 5 | N18: =SUM(H18:L18) -> 55 | O18: =+#REF! -> #REF! | P18: 75
A19: =+#REF! -> #REF! | B19: =+#REF! -> #REF! | C19: =+#REF! -> #REF! | D19: =+#REF! -> #REF! | E19: =+#REF! -> #REF! | F19: =+#REF! -> #REF! | G19: =+#REF! -> #REF! | H19: 45 | K19: 5 | L19: 5 | N19: =SUM(H19:L19) -> 55 | O19: =+#REF! -> #REF! | P19: 60
A20: =+#REF! -> #REF! | B20: =+#REF! -> #REF! | C20: =+#REF! -> #REF! | D20: =+#REF! -> #REF! | E20: =+#REF! -> #REF! | F20: =+#REF! -> #REF! | G20: =+#REF! -> #REF! | H20: 50 | K20: 5 | N20: =SUM(H20:L20) -> 55 | O20: =+#REF! -> #REF! | P20: 100
A21: =+#REF! -> #REF! | B21: =+#REF! -> #REF! | C21: =+#REF! -> #REF! | D21: =+#REF! -> #REF! | E21: =+#REF! -> #REF! | F21: =+#REF! -> #REF! | G21: =+#REF! -> #REF! | H21: 50 | K21: 5 | N21: =SUM(H21:L21) -> 55 | O21: =+#REF! -> #REF! | P21: 56
A22: =+#REF! -> #REF! | B22: =+#REF! -> #REF! | C22: =+#REF! -> #REF! | D22: =+#REF! -> #REF! | E22: =+#REF! -> #REF! | F22: =+#REF! -> #REF! | G22: =+#REF! -> #REF! | H22: 65 | K22: 5 | N22: =SUM(H22:L22) -> 70 | O22: =+#REF! -> #REF! | P22: 120
A23: =+#REF! -> #REF! | B23: =+#REF! -> #REF! | C23: =+#REF! -> #REF! | D23: =+#REF! -> #REF! | E23: =+#REF! -> #REF! | F23: =+#REF! -> #REF! | G23: =+#REF! -> #REF! | H23: 55 | K23: 5 | N23: =SUM(H23:L23) -> 60 | O23: =+#REF! -> #REF! | P23: 60
A24: =+#REF! -> #REF! | B24: =+#REF! -> #REF! | C24: =+#REF! -> #REF! | D24: =+#REF! -> #REF! | E24: =+#REF! -> #REF! | F24: =+#REF! -> #REF! | G24: =+#REF! -> #REF! | H24: 65 | K24: 5 | L24: 5 | N24: =SUM(H24:L24) -> 75 | O24: =+#REF! -> #REF! | P24: 110
A25: =+#REF! -> #REF! | B25: =+#REF! -> #REF! | C25: =+#REF! -> #REF! | D25: =+#REF! -> #REF! | E25: =+#REF! -> #REF! | F25: =+#REF! -> #REF! | G25: =+#REF! -> #REF! | H25: 65 | K25: 5 | L25: 5 | N25: =SUM(H25:L25) -> 75 | O25: =+#REF! -> #REF! | P25: 100
A26: =+#REF! -> #REF! | B26: =+#REF! -> #REF! | C26: =+#REF! -> #REF! | D26: =+#REF! -> #REF! | E26: =+#REF! -> #REF! | F26: =+#REF! -> #REF! | G26: =+#REF! -> #REF! | H26: 55 | K26: 5 | N26: =SUM(H26:L26) -> 60 | O26: =+#REF! -> #REF! | P26: 60
A27: =+#REF! -> #REF! | B27: =+#REF! -> #REF! | C27: =+#REF! -> #REF! | D27: =+#REF! -> #REF! | E27: =+#REF! -> #REF! | F27: =+#REF! -> #REF! | G27: =+#REF! -> #REF! | H27: 55 | K27: 5 | L27: 5 | N27: =SUM(H27:L27) -> 65 | O27: =+#REF! -> #REF! | P27: 120
A28: =+#REF! -> #REF! | B28: =+#REF! -> #REF! | C28: =+#REF! -> #REF! | D28: =+#REF! -> #REF! | E28: =+#REF! -> #REF! | F28: =+#REF! -> #REF! | G28: =+#REF! -> #REF! | H28: 55 | K28: 5 | N28: =SUM(H28:L28) -> 60 | O28: =+#REF! -> #REF! | P28: 60
A29: =+#REF! -> #REF! | B29: =+#REF! -> #REF! | C29: =+#REF! -> #REF! | D29: =+#REF! -> #REF! | E29: =+#REF! -> #REF! | F29: =+#REF! -> #REF! | G29: =+#REF! -> #REF! | H29: 60 | L29: 5 | N29: =SUM(H29:L29) -> 65 | O29: =+#REF! -> #REF! | P29: 75
A30: =+#REF! -> #REF! | B30: =+#REF! -> #REF! | C30: =+#REF! -> #REF! | D30: =+#REF! -> #REF! | E30: =+#REF! -> #REF! | F30: =+#REF! -> #REF! | G30: =+#REF! -> #REF! | H30: 60 | L30: 5 | N30: =SUM(H30:L30) -> 65 | O30: =+#REF! -> #REF! | P30: 110
A31: =+#REF! -> #REF! | B31: =+#REF! -> #REF! | C31: =+#REF! -> #REF! | D31: =+#REF! -> #REF! | E31: =+#REF! -> #REF! | F31: =+#REF! -> #REF! | G31: =+#REF! -> #REF! | H31: 60 | K31: 5 | L31: 5 | N31: =SUM(H31:L31) -> 70 | O31: =+#REF! -> #REF! | P31: 100
A32: =+#REF! -> #REF! | B32: =+#REF! -> #REF! | C32: =+#REF! -> #REF! | D32: =+#REF! -> #REF! | E32: =+#REF! -> #REF! | F32: =+#REF! -> #REF! | G32: =+#REF! -> #REF! | H32: 60 | K32: 5 | L32: 5 | N32: =SUM(H32:L32) -> 70 | O32: =+#REF! -> #REF! | P32: 100
A33: =+#REF! -> #REF! | B33: =+#REF! -> #REF! | C33: =+#REF! -> #REF! | D33: =+#REF! -> #REF! | E33: =+#REF! -> #REF! | F33: =+#REF! -> #REF! | G33: =+#REF! -> #REF! | H33: 55 | K33: 5 | L33: 2 | N33: =SUM(H33:L33) -> 62 | O33: =+#REF! -> #REF! | P33: 75
A34: =+#REF! -> #REF! | B34: =+#REF! -> #REF! | C34: =+#REF! -> #REF! | D34: =+#REF! -> #REF! | E34: =+#REF! -> #REF! | F34: =+#REF! -> #REF! | G34: =+#REF! -> #REF! | H34: 55 | K34: 5 | L34: 2 | N34: =SUM(H34:L34) -> 62 | O34: =+#REF! -> #REF! | P34: 80
A35: =+#REF! -> #REF! | B35: =+#REF! -> #REF! | C35: =+#REF! -> #REF! | D35: =+#REF! -> #REF! | E35: =+#REF! -> #REF! | F35: =+#REF! -> #REF! | G35: =+#REF! -> #REF! | H35: 55 | K35: 5 | N35: =SUM(H35:L35) -> 60 | O35: =+#REF! -> #REF! | P35: 60
A36: =+#REF! -> #REF! | B36: =+#REF! -> #REF! | C36: =+#REF! -> #REF! | D36: =+#REF! -> #REF! | E36: =+#REF! -> #REF! | F36: =+#REF! -> #REF! | G36: =+#REF! -> #REF! | H36: 55 | J36: 20 | K36: 3 | N36: =SUM(H36:L36) -> 78 | O36: =+#REF! -> #REF! | P36: 110
A37: =+#REF! -> #REF! | B37: =+#REF! -> #REF! | C37: =+#REF! -> #REF! | D37: =+#REF! -> #REF! | E37: =+#REF! -> #REF! | F37: =+#REF! -> #REF! | G37: =+#REF! -> #REF! | H37: 55 | J37: 20 | K37: 3 | N37: =SUM(H37:L37) -> 78 | O37: =+#REF! -> #REF! | P37: 80
A38: =+#REF! -> #REF! | B38: =+#REF! -> #REF! | C38: =+#REF! -> #REF! | D38: =+#REF! -> #REF! | E38: =+#REF! -> #REF! | F38: =+#REF! -> #REF! | G38: =+#REF! -> #REF! | H38: 63 | J38: 7 | N38: =SUM(H38:L38) -> 70 | O38: =+#REF! -> #REF! | P38: 100
A39: =+#REF! -> #REF! | B39: =+#REF! -> #REF! | C39: =+#REF! -> #REF! | D39: =+#REF! -> #REF! | E39: =+#REF! -> #REF! | F39: =+#REF! -> #REF! | G39: =+#REF! -> #REF! | H39: 63 | J39: 7 | N39: =SUM(H39:L39) -> 70 | O39: =+#REF! -> #REF! | P39: 75
A40: =+#REF! -> #REF! | B40: =+#REF! -> #REF! | C40: =+#REF! -> #REF! | D40: =+#REF! -> #REF! | E40: =+#REF! -> #REF! | F40: =+#REF! -> #REF! | G40: =+#REF! -> #REF! | H40: 63 | J40: 7 | N40: =SUM(H40:L40) -> 70 | O40: =+#REF! -> #REF! | P40: 120
B41: =+#REF! -> #REF! | C41: =+#REF! -> #REF! | D41: =+#REF! -> #REF! | E41: =+#REF! -> #REF! | F41: =+#REF! -> #REF! | G41: =+#REF! -> #REF! | H41: 23 | O41: =+#REF! -> #REF!
B42: =+#REF! -> #REF! | C42: =+#REF! -> #REF! | D42: =+#REF! -> #REF! | E42: =+#REF! -> #REF! | F42: =+#REF! -> #REF! | G42: =+#REF! -> #REF! | H42: 23 | O42: =+#REF! -> #REF!
B43: =+#REF! -> #REF! | C43: =+#REF! -> #REF! | D43: =+#REF! -> #REF! | E43: =+#REF! -> #REF! | F43: =+#REF! -> #REF! | G43: =+#REF! -> #REF! | H43: 23 | O43: =+#REF! -> #REF!
B44: =+#REF! -> #REF! | C44: =+#REF! -> #REF! | D44: =+#REF! -> #REF! | E44: =+#REF! -> #REF! | F44: =+#REF! -> #REF! | G44: =+#REF! -> #REF! | H44: 23 | O44: =+#REF! -> #REF!
B45: =+#REF! -> #REF! | C45: =+#REF! -> #REF! | D45: =+#REF! -> #REF! | E45: =+#REF! -> #REF! | F45: =+#REF! -> #REF! | G45: =+#REF! -> #REF! | H45: 23 | O45: =+#REF! -> #REF!
B46: =+#REF! -> #REF! | C46: =+#REF! -> #REF! | D46: =+#REF! -> #REF! | E46: =+#REF! -> #REF! | F46: =+#REF! -> #REF! | G46: =+#REF! -> #REF! | H46: 23 | O46: =+#REF! -> #REF!
B47: =+#REF! -> #REF! | C47: =+#REF! -> #REF! | D47: =+#REF! -> #REF! | E47: =+#REF! -> #REF! | F47: =+#REF! -> #REF! | G47: =+#REF! -> #REF! | H47: 23 | O47: =+#REF! -> #REF!
B48: =+#REF! -> #REF! | C48: =+#REF! -> #REF! | D48: =+#REF! -> #REF! | E48: =+#REF! -> #REF! | F48: =+#REF! -> #REF! | G48: =+#REF! -> #REF! | H48: 23 | O48: =+#REF! -> #REF!
B49: =+#REF! -> #REF! | C49: =+#REF! -> #REF! | D49: =+#REF! -> #REF! | E49: =+#REF! -> #REF! | F49: =+#REF! -> #REF! | G49: =+#REF! -> #REF! | H49: 23 | O49: =+#REF! -> #REF!
B50: =+#REF! -> #REF! | C50: =+#REF! -> #REF! | D50: =+#REF! -> #REF! | E50: =+#REF! -> #REF! | F50: =+#REF! -> #REF! | G50: =+#REF! -> #REF! | H50: 23 | O50: =+#REF! -> #REF!
B51: =+#REF! -> #REF! | C51: =+#REF! -> #REF! | D51: =+#REF! -> #REF! | E51: =+#REF! -> #REF! | F51: =+#REF! -> #REF! | G51: =+#REF! -> #REF! | H51: 23 | O51: =+#REF! -> #REF!
B52: =+#REF! -> #REF! | C52: =+#REF! -> #REF! | D52: =+#REF! -> #REF! | E52: =+#REF! -> #REF! | F52: =+#REF! -> #REF! | G52: =+#REF! -> #REF! | H52: 23 | O52: =+#REF! -> #REF!
B53: =+#REF! -> #REF! | C53: =+#REF! -> #REF! | D53: =+#REF! -> #REF! | E53: =+#REF! -> #REF! | F53: =+#REF! -> #REF! | G53: =+#REF! -> #REF! | H53: 23 | O53: =+#REF! -> #REF!
B56: =+#REF! -> #REF!
A57: Sigla | B57: Sigla | C57: Sec. | D57: Créd | E57: Nombre del curso | F57: Prof | G57: Requisitos | H57: UA05 | I57: UA11 | J57: UA07 | K57: FG | L57: INTERC. | N57: TOTAL | O57: Sala
A58: =+#REF! -> #REF! | B58: =+#REF! -> #REF! | C58: =+#REF! -> #REF! | D58: =+#REF! -> #REF! | E58: =+#REF! -> #REF! | F58: =+#REF! -> #REF! | G58: =+#REF! -> #REF! | H58: 45 | K58: 5 | L58: 5 | N58: =SUM(H58:L58) -> 55 | O58: =+#REF! -> #REF! | P58: 56
A59: =+#REF! -> #REF! | B59: =+#REF! -> #REF! | C59: =+#REF! -> #REF! | D59: =+#REF! -> #REF! | E59: =+#REF! -> #REF! | F59: =+#REF! -> #REF! | G59: =+#REF! -> #REF! | H59: 25 | K59: 2 | L59: 3 | N59: =SUM(H59:L59) -> 30 | O59: =+#REF! -> #REF! | P59: 60
A60: =+#REF! -> #REF! | B60: =+#REF! -> #REF! | C60: =+#REF! -> #REF! | D60: =+#REF! -> #REF! | E60: =+#REF! -> #REF! | F60: =+#REF! -> #REF! | G60: =+#REF! -> #REF! | H60: 25 | K60: 2 | L60: 3 | N60: =SUM(H60:L60) -> 30 | O60: =+#REF! -> #REF! | P60: 45
A61: =+#REF! -> #REF! | B61: =+#REF! -> #REF! | C61: =+#REF! -> #REF! | D61: =+#REF! -> #REF! | E61: =+#REF! -> #REF! | F61: =+#REF! -> #REF! | G61: =+#REF! -> #REF! | H61: 30 | K61: 3 | L61: 2 | N61: =SUM(H61:L61) -> 35 | O61: =+#REF! -> #REF! | P61: 60
A62: =+#REF! -> #REF! | B62: =+#REF! -> #REF! | C62: =+#REF! -> #REF! | D62: =+#REF! -> #REF! | E62: =+#REF! -> #REF! | F62: =+#REF! -> #REF! | G62: =+#REF! -> #REF! | H62: 55 | K62: 5 | L62: 5 | N62: =SUM(H62:L62) -> 65 | O62: =+#REF! -> #REF! | P62: 100
A63: =+#REF! -> #REF! | B63: =+#REF! -> #REF! | C63: =+#REF! -> #REF! | D63: =+#REF! -> #REF! | E63: =+#REF! -> #REF! | F63: =+#REF! -> #REF! | G63: =+#REF! -> #REF! | H63: 20 | K63: 5 | L63: 5 | N63: =SUM(H63:L63) -> 30 | O63: =+#REF! -> #REF! | P63: 56
A64: =+#REF! -> #REF! | B64: =+#REF! -> #REF! | C64: =+#REF! -> #REF! | D64: =+#REF! -> #REF! | E64: =+#REF! -> #REF! | F64: =+#REF! -> #REF! | G64: =+#REF! -> #REF! | H64: 50 | K64: 5 | L64: 2 | N64: =SUM(H64:L64) -> 57 | O64: =+#REF! -> #REF! | P64: 75
A65: =+#REF! -> #REF! | B65: =+#REF! -> #REF! | C65: =+#REF! -> #REF! | D65: =+#REF! -> #REF! | E65: =+#REF! -> #REF! | F65: =+#REF! -> #REF! | G65: =+#REF! -> #REF! | H65: 60 | K65: 3 | L65: 2 | N65: =SUM(H65:L65) -> 65 | O65: =+#REF! -> #REF! | P65: 75
B66: =+#REF! -> #REF! | C66: =+#REF! -> #REF! | D66: =+#REF! -> #REF! | E66: =+#REF! -> #REF! | F66: =+#REF! -> #REF! | G66: =+#REF! -> #REF! | H66: 50 | K66: 5 | L66: 2 | N66: =SUM(H66:L66) -> 57 | O66: =+#REF! -> #REF! | P66: 100
B67: =+#REF! -> #REF! | C67: =+#REF! -> #REF! | D67: =+#REF! -> #REF! | E67: =+#REF! -> #REF! | F67: =+#REF! -> #REF! | G67: =+#REF! -> #REF! | H67: 60 | K67: 3 | L67: 2 | N67: =SUM(H67:L67) -> 65 | O67: =+#REF! -> #REF! | P67: 100
B70: =+#REF! -> #REF!
A71: Sigla | B71: Sigla | C71: Sec. | D71: Créd | E71: Nombre del curso | F71: Prof | G71: Requisitos | H71: UA05 | I71: UA11 | J71: UA07 | K71: FG | L71: INTERC. | N71: TOTAL | O71: Sala
A72: =+#REF! -> #REF! | B72: =+#REF! -> #REF! | C72: =+#REF! -> #REF! | D72: =+#REF! -> #REF! | E72: =+#REF! -> #REF! | F72: =+#REF! -> #REF! | G72: =+#REF! -> #REF! | H72: 50 | N72: =SUM(H72:L72) -> 50 | O72: =+#REF! -> #REF! | P72: 75
A73: =+#REF! -> #REF! | B73: =+#REF! -> #REF! | C73: =+#REF! -> #REF! | D73: =+#REF! -> #REF! | E73: =+#REF! -> #REF! | F73: =+#REF! -> #REF! | G73: =+#REF! -> #REF! | H73: 50 | N73: =SUM(H73:L73) -> 50 | O73: =+#REF! -> #REF! | P73: 75
A74: =+#REF! -> #REF! | B74: =+#REF! -> #REF! | C74: =+#REF! -> #REF! | D74: =+#REF! -> #REF! | E74: =+#REF! -> #REF! | F74: =+#REF! -> #REF! | G74: =+#REF! -> #REF! | H74: 35 | N74: =SUM(H74:L74) -> 35 | O74: =+#REF! -> #REF! | P74: 56
A75: =+#REF! -> #REF! | B75: =+#REF! -> #REF! | C75: =+#REF! -> #REF! | D75: =+#REF! -> #REF! | E75: =+#REF! -> #REF! | F75: =+#REF! -> #REF! | G75: =+#REF! -> #REF! | H75: 35 | N75: =SUM(H75:L75) -> 35 | O75: =+#REF! -> #REF! | P75: 110
A76: =+#REF! -> #REF! | B76: =+#REF! -> #REF! | C76: =+#REF! -> #REF! | D76: =+#REF! -> #REF! | E76: =+#REF! -> #REF! | F76: =+#REF! -> #REF! | G76: =+#REF! -> #REF! | H76: 35 | N76: =SUM(H76:L76) -> 35 | O76: =+#REF! -> #REF! | P76: 56
A77: =+#REF! -> #REF! | B77: =+#REF! -> #REF! | C77: =+#REF! -> #REF! | D77: =+#REF! -> #REF! | E77: =+#REF! -> #REF! | F77: =+#REF! -> #REF! | G77: =+#REF! -> #REF! | H77: 60 | K77: 5 | N77: =SUM(H77:L77) -> 65 | O77: =+#REF! -> #REF! | P77: 80
A78: =+#REF! -> #REF! | B78: =+#REF! -> #REF! | C78: =+#REF! -> #REF! | D78: =+#REF! -> #REF! | E78: =+#REF! -> #REF! | F78: =+#REF! -> #REF! | G78: =+#REF! -> #REF! | H78: 60 | K78: 5 | N78: =SUM(H78:L78) -> 65 | O78: =+#REF! -> #REF! | P78: 80
A79: =+#REF! -> #REF! | B79: =+#REF! -> #REF! | C79: =+#REF! -> #REF! | D79: =+#REF! -> #REF! | E79: =+#REF! -> #REF! | F79: =+#REF! -> #REF! | G79: =+#REF! -> #REF! | H79: 60 | N79: =SUM(H79:L79) -> 60 | O79: =+#REF! -> #REF! | P79: 110
A80: =+#REF! -> #REF! | B80: =+#REF! -> #REF! | C80: =+#REF! -> #REF! | D80: =+#REF! -> #REF! | E80: =+#REF! -> #REF! | F80: =+#REF! -> #REF! | G80: =+#REF! -> #REF! | H80: 60 | N80: =SUM(H80:L80) -> 60 | O80: =+#REF! -> #REF! | P80: 110
B83: =+#REF! -> #REF! | G83: =+#REF! -> #REF!
A84: Sigla | B84: Sigla | C84: Sec. | D84: Créd | E84: Nombre del curso | F84: Prof | G84: Requisitos | H84: UA05 | I84: UA11 | J84: UA07 | K84: FG | L84: INTERC. | N84: TOTAL | O84: Sala
A85: =+#REF! -> #REF! | B85: =+#REF! -> #REF! | C85: =+#REF! -> #REF! | D85: =+#REF! -> #REF! | E85: =+#REF! -> #REF! | F85: =+#REF! -> #REF! | G85: =+#REF! -> #REF! | H85: 60 | K85: 3 | N85: =SUM(H85:L85) -> 63 | O85: =+#REF! -> #REF! | P85: 120
A86: =+#REF! -> #REF! | B86: =+#REF! -> #REF! | C86: =+#REF! -> #REF! | D86: =+#REF! -> #REF! | E86: =+#REF! -> #REF! | F86: =+#REF! -> #REF! | G86: =+#REF! -> #REF! | H86: 35 | K86: 5 | N86: =SUM(H86:L86) -> 40 | O86: =+#REF! -> #REF! | P86: 45
A87: =+#REF! -> #REF! | B87: =+#REF! -> #REF! | C87: =+#REF! -> #REF! | D87: =+#REF! -> #REF! | E87: =+#REF! -> #REF! | F87: =+#REF! -> #REF! | G87: =+#REF! -> #REF! | H87: 28 | K87: 2 | N87: =SUM(H87:L87) -> 30 | O87: =+#REF! -> #REF! | P87: 56
A88: =+#REF! -> #REF! | B88: =+#REF! -> #REF! | C88: =+#REF! -> #REF! | D88: =+#REF! -> #REF! | E88: =+#REF! -> #REF! | F88: =+#REF! -> #REF! | G88: =+#REF! -> #REF! | H88: 60 | K88: 5 | N88: =SUM(H88:L88) -> 65 | O88: =+#REF! -> #REF! | P88: 80
A89: =+#REF! -> #REF! | B89: =+#REF! -> #REF! | C89: =+#REF! -> #REF! | D89: =+#REF! -> #REF! | E89: =+#REF! -> #REF! | F89: =+#REF! -> #REF! | G89: =+#REF! -> #REF! | H89: 60 | K89: 5 | L89: 10 | N89: =SUM(H89:L89) -> 75 | O89: =+#REF! -> #REF! | P89: 110
A90: =+#REF! -> #REF! | B90: =+#REF! -> #REF! | C90: =+#REF! -> #REF! | D90: =+#REF! -> #REF! | E90: =+#REF! -> #REF! | F90: =+#REF! -> #REF! | G90: =+#REF! -> #REF! | H90: 60 | K90: 3 | L90: 2 | N90: =SUM(H90:L90) -> 65 | O90: =+#REF! -> #REF! | P90: 110
A91: =+#REF! -> #REF! | B91: =+#REF! -> #REF! | C91: =+#REF! -> #REF! | D91: =+#REF! -> #REF! | E91: =+#REF! -> #REF! | F91: =+#REF! -> #REF! | G91: =+#REF! -> #REF! | H91: 55 | K91: 3 | L91: 2 | N91: =SUM(H91:L91) -> 60 | O91: =+#REF! -> #REF! | P91: 60
A92: =+#REF! -> #REF! | B92: =+#REF! -> #REF! | C92: =+#REF! -> #REF! | D92: =+#REF! -> #REF! | E92: =+#REF! -> #REF! | F92: =+#REF! -> #REF! | G92: =+#REF! -> #REF! | H92: 60 | K92: 3 | L92: 2 | N92: =SUM(H92:L92) -> 65 | O92: =+#REF! -> #REF!
A93: =+#REF! -> #REF! | B93: =+#REF! -> #REF! | C93: =+#REF! -> #REF! | D93: =+#REF! -> #REF! | E93: =+#REF! -> #REF! | F93: =+#REF! -> #REF! | G93: =+#REF! -> #REF! | H93: 60 | K93: 3 | L93: 2 | N93: =SUM(H93:L93) -> 65 | O93: =+#REF! -> #REF! | P93: 75
B95: =+#REF! -> #REF!
A96: Sigla | B96: Sigla | C96: Sec. | D96: Créd | E96: Nombre del curso | F96: Prof | G96: Requisitos | I96: UA01 | J96: UA10 | K96: FG | L96: INTERC. | N96: TOTAL | O96: Sala
A97: =+#REF! -> #REF! | B97: =+#REF! -> #REF! | C97: =+#REF! -> #REF! | D97: =+#REF! -> #REF! | E97: =+#REF! -> #REF! | F97: =+#REF! -> #REF! | G97: =+#REF! -> #REF! | I97: 50 | J97: 4 | K97: 4 | L97: 2 | N97: =SUM(I97:L97) -> 60 | O97: =+#REF! -> #REF!
A98: =+#REF! -> #REF! | B98: =+#REF! -> #REF! | C98: =+#REF! -> #REF! | D98: =+#REF! -> #REF! | E98: =+#REF! -> #REF! | F98: =+#REF! -> #REF! | G98: =+#REF! -> #REF! | I98: 50 | J98: 4 | K98: 4 | L98: 2 | N98: =SUM(I98:L98) -> 60 | O98: =+#REF! -> #REF!
A99: =+#REF! -> #REF! | B99: =+#REF! -> #REF! | C99: =+#REF! -> #REF! | D99: =+#REF! -> #REF! | E99: =+#REF! -> #REF! | F99: =+#REF! -> #REF! | G99: =+#REF! -> #REF! | I99: 20 | K99: 5 | L99: 5 | N99: =SUM(I99:L99) -> 30 | O99: =+#REF! -> #REF!
A100: =+#REF! -> #REF! | B100: =+#REF! -> #REF! | C100: =+#REF! -> #REF! | D100: =+#REF! -> #REF! | E100: =+#REF! -> #REF! | F100: =+#REF! -> #REF! | G100: =+#REF! -> #REF! | K100: 30 | L100: 10 | N100: =SUM(I100:L100) -> 40 | O100: =+#REF! -> #REF! | P100: 56
A101: =+#REF! -> #REF! | B101: =+#REF! -> #REF! | C101: =+#REF! -> #REF! | D101: =+#REF! -> #REF! | E101: =+#REF! -> #REF! | F101: =+#REF! -> #REF! | G101: =+#REF! -> #REF! | N101: =SUM(I101:L101) -> 0 | O101: =+#REF! -> #REF!
B103: =+#REF! -> #REF! | G103: =+#REF! -> #REF!
A105: Sigla | B105: Sigla | C105: Sec. | D105: Créd | E105: Nombre del curso | F105: Prof | G105: Requisitos | H105: UA05 | I105: UA11 | J105: UA07 | K105: FG | L105: INTERC. | N105: TOTAL | O105: Sala
A106: =+#REF! -> #REF! | B106: =+#REF! -> #REF! | C106: =+#REF! -> #REF! | D106: =+#REF! -> #REF! | E106: =+#REF! -> #REF! | F106: =+#REF! -> #REF! | G106: =+#REF! -> #REF! | H106: 60 | K106: 10 | L106: 5 | N106: =SUM(H106:L106) -> 75 | O106: =+#REF! -> #REF! | P106: 120
A107: =+#REF! -> #REF! | B107: =+#REF! -> #REF! | C107: =+#REF! -> #REF! | D107: =+#REF! -> #REF! | E107: =+#REF! -> #REF! | F107: =+#REF! -> #REF! | G107: =+#REF! -> #REF! | H107: 55 | I107: 6 | J107: 11 | K107: 4 | L107: 2 | N107: =SUM(H107:L107) -> 78 | O107: =+#REF! -> #REF! | P107: 100
A108: =+#REF! -> #REF! | B108: =+#REF! -> #REF! | C108: =+#REF! -> #REF! | D108: =+#REF! -> #REF! | E108: =+#REF! -> #REF! | F108: =+#REF! -> #REF! | G108: =+#REF! -> #REF! | H108: 55 | I108: 6 | J108: 11 | K108: 4 | L108: 2 | N108: =SUM(H108:L108) -> 78 | O108: =+#REF! -> #REF! | P108: 100
A109: =+#REF! -> #REF! | B109: =+#REF! -> #REF! | C109: =+#REF! -> #REF! | D109: =+#REF! -> #REF! | E109: =+#REF! -> #REF! | F109: =+#REF! -> #REF! | G109: =+#REF! -> #REF! | H109: 55 | I109: 6 | J109: 11 | K109: 4 | L109: 2 | M109: 0 | N109: =SUM(H109:M109) -> 78 | O109: =+#REF! -> #REF! | P109: 80
A110: =+#REF! -> #REF! | B110: =+#REF! -> #REF! | C110: =+#REF! -> #REF! | D110: =+#REF! -> #REF! | E110: =+#REF! -> #REF! | F110: =+#REF! -> #REF! | G110: =+#REF! -> #REF! | H110: 55 | I110: 6 | J110: 11 | K110: 4 | L110: 2 | M110: 0 | N110: =SUM(H110:M110) -> 78 | O110: =+#REF! -> #REF! | P110: 80
...

Sheet Hoja1
E1: PONTIFICIA UNIVERSIDAD CATOLICA DE CHILE
E2: ESCUELA DE ADMINISTRACION
E3: PROGRAMACIÓN DE CURSOS SEGUNDO SEMESTRE DEL 2006
A5: CURSOS MINIMOS LICENCIATURA
M6: VACANTES
A7: Sigla | B7: Sec. | C7: Créd | D7: Nombre del curso | E7: Prof | F7: RUT | G7: Requisitos | H7: Hor. | I7: Sala | J7: Hor. | K7: Sala | M7: UA05 | N7: UA11 | O7: UA07 | P7: FG | Q7: INTERCAMBIO | R7: TOTAL | S7: TOTAL
A8: =+#REF! -> #REF! | B8: =+#REF! -> #REF! | C8: =+#REF! -> #REF! | D8: =+#REF! -> #REF! | E8: =+#REF! -> #REF! | F8: 5593247-6 | G8: =IF(D8="","",VLOOKUP(MID(A8,1,7),#REF!,3,FALSE)) -> #REF! | H8: =+#REF! -> #REF! | I8: =+#REF! -> #REF! | J8: =+#REF! -> #REF! | K8: =+#REF! -> #REF! | M8: =+VACANTES!H8 -> 55 | N8: =+VACANTES!I8 -> 0 | O8: =+VACANTES!J8 -> 0 | P8: =+VACANTES!K8 -> 5 | Q8: =+VACANTES!L8 -> 5 | R8: =+VACANTES!N8 -> 65 | S8: =+R8-Q8 -> 60
A9: =+#REF! -> #REF! | B9: =+#REF! -> #REF! | C9: =+#REF! -> #REF! | D9: =+#REF! -> #REF! | E9: =+#REF! -> #REF! | F9: 6062116-0 | G9: =IF(D9="","",VLOOKUP(MID(A9,1,7),#REF!,3,FALSE)) -> #REF! | H9: =+#REF! -> #REF! | I9: =+#REF! -> #REF! | J9: =+#REF! -> #REF! | K9: =+#REF! -> #REF! | M9: =+VACANTES!H9 -> 55 | N9: =+VACANTES!I9 -> 0 | O9: =+VACANTES!J9 -> 0 | P9: =+VACANTES!K9 -> 5 | Q9: =+VACANTES!L9 -> 5 | R9: =+VACANTES!N9 -> 65 | S9: =+R9-Q9 -> 60
A10: =+#REF! -> #REF! | B10: =+#REF! -> #REF! | C10: =+#REF! -> #REF! | D10: =+#REF! -> #REF! | E10: N.N | G10: =IF(D10="","",VLOOKUP(MID(A10,1,7),#REF!,3,FALSE)) -> #REF! | J10: =+#REF! -> #REF! | K10: =+#REF! -> #REF! | M10: =+VACANTES!H10 -> 55 | N10: =+VACANTES!I10 -> 0 | O10: =+VACANTES!J10 -> 0 | P10: =+VACANTES!K10 -> 5 | Q10: =+VACANTES!L10 -> 5 | R10: =+VACANTES!N10 -> 65 | S10: =+R10-Q10 -> 60
A11: =+#REF! -> #REF! | B11: =+#REF! -> #REF! | C11: =+#REF! -> #REF! | D11: =+#REF! -> #REF! | E11: =+#REF! -> #REF! | F11: 8122891-4 | G11: =IF(D11="","",VLOOKUP(MID(A11,1,7),#REF!,3,FALSE)) -> #REF! | H11: =+#REF! -> #REF! | I11: =+#REF! -> #REF! | J11: =+#REF! -> #REF! | K11: =+#REF! -> #REF! | M11: =+VACANTES!H11 -> 55 | N11: =+VACANTES!I11 -> 0 | O11: =+VACANTES!J11 -> 0 | P11: =+VACANTES!K11 -> 5 | Q11: =+VACANTES!L11 -> 5 | R11: =+VACANTES!N11 -> 65 | S11: =+R11-Q11 -> 60
A12: =+#REF! -> #REF! | B12: =+#REF! -> #REF! | C12: =+#REF! -> #REF! | D12: =+#REF! -> #REF! | E12: N.N | G12: =IF(D12="","",VLOOKUP(MID(A12,1,7),#REF!,3,FALSE)) -> #REF! | I12: =+#REF! -> #REF! | J12: =+#REF! -> #REF! | K12: =+#REF! -> #REF! | M12: =+VACANTES!H12 -> 40 | N12: =+VACANTES!I12 -> 0 | O12: =+VACANTES!J12 -> 15 | P12: =+VACANTES!K12 -> 5 | Q12: =+VACANTES!L12 -> 3 | R12: =+VACANTES!N12 -> 63 | S12: =+R12-Q12 -> 60
A13: =+#REF! -> #REF! | B13: =+#REF! -> #REF! | C13: =+#REF! -> #REF! | D13: =+#REF! -> #REF! | E13: =+#REF! -> #REF! | G13: =IF(D13="","",VLOOKUP(MID(A13,1,7),#REF!,3,FALSE)) -> #REF! | H13: =+#REF! -> #REF! | I13: =+#REF! -> #REF! | J13: =+#REF! -> #REF! | K13: =+#REF! -> #REF! | M13: =+VACANTES!H13 -> 40 | N13: =+VACANTES!I13 -> 0 | O13: =+VACANTES!J13 -> 15 | P13: =+VACANTES!K13 -> 5 | Q13: =+VACANTES!L13 -> 3 | R13: =+VACANTES!N13 -> 63 | S13: =+R13-Q13 -> 60
A14: =+#REF! -> #REF! | B14: =+#REF! -> #REF! | C14: =+#REF! -> #REF! | D14: =+#REF! -> #REF! | E14: =+#REF! -> #REF! | F14: 7274560-4 | G14: =IF(D14="","",VLOOKUP(MID(A14,1,7),#REF!,3,FALSE)) -> #REF! | H14: =+#REF! -> #REF! | I14: =+#REF! -> #REF! | J14: =+#REF! -> #REF! | K14: =+#REF! -> #REF! | M14: =+VACANTES!H14 -> 51 | N14: =+VACANTES!I14 -> 0 | O14: =+VACANTES!J14 -> 14 | P14: =+VACANTES!K14 -> 5 | Q14: =+VACANTES!L14 -> 0 | R14: =+VACANTES!N14 -> 70 | S14: =+R14-Q14 -> 70
A15: =+#REF! -> #REF! | B15: =+#REF! -> #REF! | C15: =+#REF! -> #REF! | D15: =+#REF! -> #REF! | E15: =+#REF! -> #REF! | F15: 15379452-9 | G15: =IF(D15="","",VLOOKUP(MID(A15,1,7),#REF!,3,FALSE)) -> #REF! | H15: =+#REF! -> #REF! | I15: =+#REF! -> #REF! | J15: =+#REF! -> #REF! | K15: =+#REF! -> #REF! | M15: =+VACANTES!H15 -> 51 | N15: =+VACANTES!I15 -> 0 | O15: =+VACANTES!J15 -> 14 | P15: =+VACANTES!K15 -> 5 | Q15: =+VACANTES!L15 -> 0 | R15: =+VACANTES!N15 -> 70 | S15: =+R15-Q15 -> 70
A16: =+#REF! -> #REF! | B16: =+#REF! -> #REF! | C16: =+#REF! -> #REF! | D16: =+#REF! -> #REF! | E16: =+#REF! -> #REF! | F16: 15312093-5 | G16: =IF(D16="","",VLOOKUP(MID(A16,1,7),#REF!,3,FALSE)) -> #REF! | H16: =+#REF! -> #REF! | I16: =+#REF! -> #REF! | J16: =+#REF! -> #REF! | K16: =+#REF! -> #REF! | M16: =+VACANTES!H16 -> 51 | N16: =+VACANTES!I16 -> 0 | O16: =+VACANTES!J16 -> 14 | P16: =+VACANTES!K16 -> 5 | Q16: =+VACANTES!L16 -> 0 | R16: =+VACANTES!N16 -> 70 | S16: =+R16-Q16 -> 70
A17: =+#REF! -> #REF! | B17: =+#REF! -> #REF! | C17: =+#REF! -> #REF! | D17: =+#REF! -> #REF! | E17: =+#REF! -> #REF! | F17: 10034247-2 | G17: =IF(D17="","",VLOOKUP(MID(A17,1,7),#REF!,3,FALSE)) -> #REF! | H17: =+#REF! -> #REF! | I17: =+#REF! -> #REF! | J17: =+#REF! -> #REF! | K17: =+#REF! -> #REF! | M17: =+VACANTES!H17 -> 51 | N17: =+VACANTES!I17 -> 0 | O17: =+VACANTES!J17 -> 14 | P17: =+VACANTES!K17 -> 5 | Q17: =+VACANTES!L17 -> 0 | R17: =+VACANTES!N17 -> 70 | S17: =+R17-Q17 -> 70
A18: =+#REF! -> #REF! | B18: =+#REF! -> #REF! | C18: =+#REF! -> #REF! | D18: =+#REF! -> #REF! | E18: =+#REF! -> #REF! | F18: 9580246-K | G18: =IF(D18="","",VLOOKUP(MID(A18,1,7),#REF!,3,FALSE)) -> #REF! | H18: =+#REF! -> #REF! | I18: =+#REF! -> #REF! | J18: =+#REF! -> #REF! | K18: =+#REF! -> #REF! | M18: =+VACANTES!H18 -> 45 | N18: =+VACANTES!I18 -> 0 | O18: =+VACANTES!J18 -> 0 | P18: =+VACANTES!K18 -> 5 | Q18: =+VACANTES!L18 -> 5 | R18: =+VACANTES!N18 -> 55 | S18: =+R18-Q18 -> 50
A19: =+#REF! -> #REF! | B19: =+#REF! -> #REF! | C19: =+#REF! -> #REF! | D19: =+#REF! -> #REF! | E19: =+#REF! -> #REF! | F19: 8530082-2 | G19: =IF(D19="","",VLOOKUP(MID(A19,1,7),#REF!,3,FALSE)) -> #REF! | H19: =+#REF! -> #REF! | I19: =+#REF! -> #REF! | J19: =+#REF! -> #REF! | K19: =+#REF! -> #REF! | M19: =+VACANTES!H19 -> 45 | N19: =+VACANTES!I19 -> 0 | O19: =+VACANTES!J19 -> 0 | P19: =+VACANTES!K19 -> 5 | Q19: =+VACANTES!L19 -> 5 | R19: =+VACANTES!N19 -> 55 | S19: =+R19-Q19 -> 50
A20: =+#REF! -> #REF! | B20: =+#REF! -> #REF! | C20: =+#REF! -> #REF! | D20: =+#REF! -> #REF! | E20: =+#REF! -> #REF! | F20: 9681304-K | G20: =IF(D20="","",VLOOKUP(MID(A20,1,7),#REF!,3,FALSE)) -> #REF! | H20: =+#REF! -> #REF! | I20: =+#REF! -> #REF! | J20: =+#REF! -> #REF! | K20: =+#REF! -> #REF! | M20: =+VACANTES!H20 -> 50 | N20: =+VACANTES!I20 -> 0 | O20: =+VACANTES!J20 -> 0 | P20: =+VACANTES!K20 -> 5 | Q20: =+VACANTES!L20 -> 0 | R20: =+VACANTES!N20 -> 55 | S20: =+R20-Q20 -> 55
A21: =+#REF! -> #REF! | B21: =+#REF! -> #REF! | C21: =+#REF! -> #REF! | D21: =+#REF! -> #REF! | E21: N.N | G21: =IF(D21="","",VLOOKUP(MID(A21,1,7),#REF!,3,FALSE)) -> #REF! | H21: =+#REF! -> #REF! | I21: =+#REF! -> #REF! | J21: =+#REF! -> #REF! | K21: =+#REF! -> #REF! | M21: =+VACANTES!H21 -> 50 | N21: =+VACANTES!I21 -> 0 | O21: =+VACANTES!J21 -> 0 | P21: =+VACANTES!K21 -> 5 | Q21: =+VACANTES!L21 -> 0 | R21: =+VACANTES!N21 -> 55 | S21: =+R21-Q21 -> 55
A22: =+#REF! -> #REF! | B22: =+#REF! -> #REF! | C22: =+#REF! -> #REF! | D22: =+#REF! -> #REF! | E22: =+#REF! -> #REF! | F22: 9669736-8 | G22: =IF(D22="","",VLOOKUP(MID(A22,1,7),#REF!,3,FALSE)) -> #REF! | H22: =+#REF! -> #REF! | I22: =+#REF! -> #REF! | J22: =+#REF! -> #REF! | K22: =+#REF! -> #REF! | M22: =+VACANTES!H22 -> 65 | N22: =+VACANTES!I22 -> 0 | O22: =+VACANTES!J22 -> 0 | P22: =+VACANTES!K22 -> 5 | Q22: =+VACANTES!L22 -> 0 | R22: =+VACANTES!N22 -> 70 | S22: =+R22-Q22 -> 70
A23: =+#REF! -> #REF! | B23: =+#REF! -> #REF! | C23: =+#REF! -> #REF! | D23: =+#REF! -> #REF! | E23: =+#REF! -> #REF! | F23: 13702582-5 | G23: =IF(D23="","",VLOOKUP(MID(A23,1,7),#REF!,3,FALSE)) -> #REF! | H23: =+#REF! -> #REF! | I23: =+#REF! -> #REF! | J23: =+#REF! -> #REF! | K23: =+#REF! -> #REF! | M23: =+VACANTES!H23 -> 55 | N23: =+VACANTES!I23 -> 0 | O23: =+VACANTES!J23 -> 0 | P23: =+VACANTES!K23 -> 5 | Q23: =+VACANTES!L23 -> 0 | R23: =+VACANTES!N23 -> 60 | S23: =+R23-Q23 -> 60
A24: =+#REF! -> #REF! | B24: =+#REF! -> #REF! | C24: =+#REF! -> #REF! | D24: =+#REF! -> #REF! | E24: =+#REF! -> #REF! | F24: 3639231-2 | G24: =IF(D24="","",VLOOKUP(MID(A24,1,7),#REF!,3,FALSE)) -> #REF! | H24: =+#REF! -> #REF! | I24: =+#REF! -> #REF! | J24: =+#REF! -> #REF! | K24: =+#REF! -> #REF! | M24: =+VACANTES!H24 -> 65 | N24: =+VACANTES!I24 -> 0 | O24: =+VACANTES!J24 -> 0 | P24: =+VACANTES!K24 -> 5 | Q24: =+VACANTES!L24 -> 5 | R24: =+VACANTES!N24 -> 75 | S24: =+R24-Q24 -> 70
A25: =+#REF! -> #REF! | B25: =+#REF! -> #REF! | C25: =+#REF! -> #REF! | D25: =+#REF! -> #REF! | E25: =+#REF! -> #REF! | F25: 13039736-0 | G25: =IF(D25="","",VLOOKUP(MID(A25,1,7),#REF!,3,FALSE)) -> #REF! | H25: =+#REF! -> #REF! | I25: =+#REF! -> #REF! | J25: =+#REF! -> #REF! | K25: =+#REF! -> #REF! | M25: =+VACANTES!H25 -> 65 | N25: =+VACANTES!I25 -> 0 | O25: =+VACANTES!J25 -> 0 | P25: =+VACANTES!K25 -> 5 | Q25: =+VACANTES!L25 -> 5 | R25: =+VACANTES!N25 -> 75 | S25: =+R25-Q25 -> 70
A26: =+#REF! -> #REF! | B26: =+#REF! -> #REF! | C26: =+#REF! -> #REF! | D26: =+#REF! -> #REF! | E26: =+#REF! -> #REF! | F26: 17947504-9 | G26: =IF(D26="","",VLOOKUP(MID(A26,1,7),#REF!,3,FALSE)) -> #REF! | H26: =+#REF! -> #REF! | I26: =+#REF! -> #REF! | J26: =+#REF! -> #REF! | K26: =+#REF! -> #REF! | M26: =+VACANTES!H26 -> 55 | N26: =+VACANTES!I26 -> 0 | O26: =+VACANTES!J26 -> 0 | P26: =+VACANTES!K26 -> 5 | Q26: =+VACANTES!L26 -> 0 | R26: =+VACANTES!N26 -> 60 | S26: =+R26-Q26 -> 60
A27: =+#REF! -> #REF! | B27: =+#REF! -> #REF! | C27: =+#REF! -> #REF! | D27: =+#REF! -> #REF! | E27: =+#REF! -> #REF! | F27: 7274560-4 | G27: =IF(D27="","",VLOOKUP(MID(A27,1,7),#REF!,3,FALSE)) -> #REF! | H27: =+#REF! -> #REF! | I27: =+#REF! -> #REF! | J27: =+#REF! -> #REF! | K27: =+#REF! -> #REF! | M27: =+VACANTES!H27 -> 55 | N27: =+VACANTES!I27 -> 0 | O27: =+VACANTES!J27 -> 0 | P27: =+VACANTES!K27 -> 5 | Q27: =+VACANTES!L27 -> 5 | R27: =+VACANTES!N27 -> 65 | S27: =+R27-Q27 -> 60
A28: =+#REF! -> #REF! | B28: =+#REF! -> #REF! | C28: =+#REF! -> #REF! | D28: =+#REF! -> #REF! | E28: =+#REF! -> #REF! | G28: =IF(D28="","",VLOOKUP(MID(A28,1,7),#REF!,3,FALSE)) -> #REF! | H28: =+#REF! -> #REF! | I28: =+#REF! -> #REF! | J28: =+#REF! -> #REF! | K28: =+#REF! -> #REF! | M28: =+VACANTES!H28 -> 55 | N28: =+VACANTES!I28 -> 0 | O28: =+VACANTES!J28 -> 0 | P28: =+VACANTES!K28 -> 5 | Q28: =+VACANTES!L28 -> 0 | R28: =+VACANTES!N28 -> 60 | S28: =+R28-Q28 -> 60
A29: =+#REF! -> #REF! | B29: =+#REF! -> #REF! | C29: =+#REF! -> #REF! | D29: =+#REF! -> #REF! | E29: =+#REF! -> #REF! | G29: =IF(D29="","",VLOOKUP(MID(A29,1,7),#REF!,3,FALSE)) -> #REF! | H29: =+#REF! -> #REF! | I29: =+#REF! -> #REF! | J29: =+#REF! -> #REF! | K29: =+#REF! -> #REF! | M29: =+VACANTES!H29 -> 60 | N29: =+VACANTES!I29 -> 0 | O29: =+VACANTES!J29 -> 0 | P29: =+VACANTES!K29 -> 0 | Q29: =+VACANTES!L29 -> 5 | R29: =+VACANTES!N29 -> 65 | S29: =+R29-Q29 -> 60
A30: =+#REF! -> #REF! | B30: =+#REF! -> #REF! | C30: =+#REF! -> #REF! | D30: =+#REF! -> #REF! | E30: =+#REF! -> #REF! | F30: 5573978-1 | G30: =IF(D30="","",VLOOKUP(MID(A30,1,7),#REF!,3,FALSE)) -> #REF! | H30: =+#REF! -> #REF! | I30: =+#REF! -> #REF! | J30: =+#REF! -> #REF! | K30: =+#REF! -> #REF! | M30: =+VACANTES!H30 -> 60 | N30: =+VACANTES!I30 -> 0 | O30: =+VACANTES!J30 -> 0 | P30: =+VACANTES!K30 -> 0 | Q30: =+VACANTES!L30 -> 5 | R30: =+VACANTES!N30 -> 65 | S30: =+R30-Q30 -> 60
A31: =+#REF! -> #REF! | B31: =+#REF! -> #REF! | C31: =+#REF! -> #REF! | D31: =+#REF! -> #REF! | E31: =+#REF! -> #REF! | F31: 2285027-K | G31: =IF(D31="","",VLOOKUP(MID(A31,1,7),#REF!,3,FALSE)) -> #REF! | H31: =+#REF! -> #REF! | I31: =+#REF! -> #REF! | J31: =+#REF! -> #REF! | K31: =+#REF! -> #REF! | M31: =+VACANTES!H31 -> 60 | N31: =+VACANTES!I31 -> 0 | O31: =+VACANTES!J31 -> 0 | P31: =+VACANTES!K31 -> 5 | Q31: =+VACANTES!L31 -> 5 | R31: =+VACANTES!N31 -> 70 | S31: =+R31-Q31 -> 65
A32: =+#REF! -> #REF! | B32: =+#REF! -> #REF! | C32: =+#REF! -> #REF! | D32: =+#REF! -> #REF! | E32: =+#REF! -> #REF! | F32: 7006273-9 | G32: =IF(D32="","",VLOOKUP(MID(A32,1,7),#REF!,3,FALSE)) -> #REF! | H32: =+#REF! -> #REF! | I32: =+#REF! -> #REF! | J32: =+#REF! -> #REF! | K32: =+#REF! -> #REF! | M32: =+VACANTES!H32 -> 60 | N32: =+VACANTES!I32 -> 0 | O32: =+VACANTES!J32 -> 0 | P32: =+VACANTES!K32 -> 5 | Q32: =+VACANTES!L32 -> 5 | R32: =+VACANTES!N32 -> 70 | S32: =+R32-Q32 -> 65
A33: =+#REF! -> #REF! | B33: =+#REF! -> #REF! | C33: =+#REF! -> #REF! | D33: =+#REF! -> #REF! | E33: =+#REF! -> #REF! | F33: 9156819-5 | G33: =IF(D33="","",VLOOKUP(MID(A33,1,7),#REF!,3,FALSE)) -> #REF! | J33: =+#REF! -> #REF! | K33: =+#REF! -> #REF! | M33: =+VACANTES!H33 -> 55 | N33: =+VACANTES!I33 -> 0 | O33: =+VACANTES!J33 -> 0 | P33: =+VACANTES!K33 -> 5 | Q33: =+VACANTES!L33 -> 2 | R33: =+VACANTES!N33 -> 62 | S33: =+R33-Q33 -> 60
A34: =+#REF! -> #REF! | B34: =+#REF! -> #REF! | C34: =+#REF! -> #REF! | D34: =+#REF! -> #REF! | E34: =+#REF! -> #REF! | F34: 10107406-4 | G34: =IF(D34="","",VLOOKUP(MID(A34,1,7),#REF!,3,FALSE)) -> #REF! | H34: =+#REF! -> #REF! | I34: =+#REF! -> #REF! | J34: =+#REF! -> #REF! | K34: =+#REF! -> #REF! | M34: =+VACANTES!H34 -> 55 | N34: =+VACANTES!I34 -> 0 | O34: =+VACANTES!J34 -> 0 | P34: =+VACANTES!K34 -> 5 | Q34: =+VACANTES!L34 -> 2 | R34: =+VACANTES!N34 -> 62 | S34: =+R34-Q34 -> 60
A35: =+#REF! -> #REF! | B35: =+#REF! -> #REF! | C35: =+#REF! -> #REF! | D35: =+#REF! -> #REF! | E35: =+#REF! -> #REF! | G35: =IF(D35="","",VLOOKUP(MID(A35,1,7),#REF!,3,FALSE)) -> #REF! | H35: =+#REF! -> #REF! | I35: =+#REF! -> #REF! | J35: =+#REF! -> #REF! | K35: =+#REF! -> #REF! | M35: =+VACANTES!H35 -> 55 | N35: =+VACANTES!I35 -> 0 | O35: =+VACANTES!J35 -> 0 | P35: =+VACANTES!K35 -> 5 | Q35: =+VACANTES!L35 -> 0 | R35: =+VACANTES!N35 -> 60 | S35: =+R35-Q35 -> 60
A36: =+#REF! -> #REF! | B36: =+#REF! -> #REF! | C36: =+#REF! -> #REF! | D36: =+#REF! -> #REF! | E36: =+#REF! -> #REF! | G36: =IF(D36="","",VLOOKUP(MID(A36,1,7),#REF!,3,FALSE)) -> #REF! | H36: =#REF! -> #REF! | I36: =+#REF! -> #REF! | J36: =+#REF! -> #REF! | K36: =+#REF! -> #REF! | M36: =+VACANTES!H36 -> 55 | N36: =+VACANTES!I36 -> 0 | O36: =+VACANTES!J36 -> 20 | P36: =+VACANTES!K36 -> 3 | Q36: =+VACANTES!L36 -> 0 | R36: =+VACANTES!N36 -> 78 | S36: =+R36-Q36 -> 78
A37: =+#REF! -> #REF! | B37: =+#REF! -> #REF! | C37: =+#REF! -> #REF! | D37: =+#REF! -> #REF! | E37: =+#REF! -> #REF! | G37: =IF(D37="","",VLOOKUP(MID(A37,1,7),#REF!,3,FALSE)) -> #REF! | H37: =+#REF! -> #REF! | I37: =+#REF! -> #REF! | J37: =+#REF! -> #REF! | K37: =+#REF! -> #REF! | M37: =+VACANTES!H37 -> 55 | N37: =+VACANTES!I37 -> 0 | O37: =+VACANTES!J37 -> 20 | P37: =+VACANTES!K37 -> 3 | Q37: =+VACANTES!L37 -> 0 | R37: =+VACANTES!N37 -> 78 | S37: =+R37-Q37 -> 78
A38: =+#REF! -> #REF! | B38: =+#REF! -> #REF! | C38: =+#REF! -> #REF! | D38: =+#REF! -> #REF! | E38: =+#REF! -> #REF! | F38: 5486416-7 | G38: =IF(D38="","",VLOOKUP(MID(A38,1,7),#REF!,3,FALSE)) -> #REF! | H38: =+#REF! -> #REF! | I38: =+#REF! -> #REF! | J38: =+#REF! -> #REF! | K38: =+#REF! -> #REF! | M38: =+VACANTES!H38 -> 63 | N38: =+VACANTES!I38 -> 0 | O38: =+VACANTES!J38 -> 7 | P38: =+VACANTES!K38 -> 0 | Q38: =+VACANTES!L38 -> 0 | R38: =+VACANTES!N38 -> 70 | S38: =+R38-Q38 -> 70
A39: =+#REF! -> #REF! | B39: =+#REF! -> #REF! | C39: =+#REF! -> #REF! | D39: =+#REF! -> #REF! | E39: =+#REF! -> #REF! | F39: 6443418-7 | G39: =IF(D39="","",VLOOKUP(MID(A39,1,7),#REF!,3,FALSE)) -> #REF! | H39: =+#REF! -> #REF! | I39: =+#REF! -> #REF! | J39: =+#REF! -> #REF! | K39: =+#REF! -> #REF! | M39: =+VACANTES!H39 -> 63 | N39: =+VACANTES!I39 -> 0 | O39: =+VACANTES!J39 -> 7 | P39: =+VACANTES!K39 -> 0 | Q39: =+VACANTES!L39 -> 0 | R39: =+VACANTES!N39 -> 70 | S39: =+R39-Q39 -> 70
A40: =+#REF! -> #REF! | B40: =+#REF! -> #REF! | C40: =+#REF! -> #REF! | D40: =+#REF! -> #REF! | E40: =+#REF! -> #REF! | F40: 8542877-2 | G40: =IF(D40="","",VLOOKUP(MID(A40,1,7),#REF!,3,FALSE)) -> #REF! | H40: =+#REF! -> #REF! | I40: =+#REF! -> #REF! | J40: =+#REF! -> #REF! | K40: =+#REF! -> #REF! | M40: =+VACANTES!H40 -> 63 | N40: =+VACANTES!I40 -> 0 | O40: =+VACANTES!J40 -> 7 | P40: =+VACANTES!K40 -> 0 | Q40: =+VACANTES!L40 -> 0 | R40: =+VACANTES!N40 -> 70 | S40: =+R40-Q40 -> 70
A43: CURSOS OPTATIVOS LICENCIATURA | G43: =IF(D43="","",VLOOKUP(MID(A43,1,7),#REF!,3,FALSE))
A44: Sigla | B44: Sec. | C44: Créd | D44: Nombre del curso | E44: Prof | G44: Requisitos | H44: Hor. | I44: Sala | J44: Hor. | K44: Sala | M44: =+VACANTES!H57 -> UA05 | N44: =+VACANTES!I57 -> UA11 | O44: =+VACANTES!J57 -> UA07 | P44: =+VACANTES!K57 -> FG | Q44: =+VACANTES!L57 -> INTERC. | R44: =+VACANTES!N57 -> TOTAL | S44: TOTAL
A45: =+#REF! -> #REF! | B45: =+#REF! -> #REF! | C45: =+#REF! -> #REF! | D45: =+#REF! -> #REF! | E45: =+#REF! -> #REF! | F45: 10193202-8 | G45: =IF(D45="","",VLOOKUP(MID(A45,1,7),#REF!,3,FALSE)) -> #REF! | H45: =+#REF! -> #REF! | I45: =+#REF! -> #REF! | J45: =+#REF! -> #REF! | K45: =+#REF! -> #REF! | M45: =+VACANTES!H58 -> 45 | N45: =+VACANTES!I58 -> 0 | O45: =+VACANTES!J58 -> 0 | P45: =+VACANTES!K58 -> 5 | Q45: =+VACANTES!L58 -> 5 | R45: =+VACANTES!N58 -> 55 | S45: =+R45-Q45 -> 50
A46: =+#REF! -> #REF! | B46: =+#REF! -> #REF! | C46: =+#REF! -> #REF! | D46: =+#REF! -> #REF! | E46: =+#REF! -> #REF! | F46: 5593247-6 | G46: =IF(D46="","",VLOOKUP(MID(A46,1,7),#REF!,3,FALSE)) -> #REF! | H46: =+#REF! -> #REF! | I46: =+#REF! -> #REF! | J46: =+#REF! -> #REF! | K46: =+#REF! -> #REF! | M46: =+VACANTES!H59 -> 25 | N46: =+VACANTES!I59 -> 0 | O46: =+VACANTES!J59 -> 0 | P46: =+VACANTES!K59 -> 2 | Q46: =+VACANTES!L59 -> 3 | R46: =+VACANTES!N59 -> 30 | S46: =+R46-Q46 -> 27
A47: =+#REF! -> #REF! | B47: =+#REF! -> #REF! | C47: =+#REF! -> #REF! | D47: =+#REF! -> #REF! | E47: =+#REF! -> #REF! | F47: 5469598-5 | G47: =IF(D47="","",VLOOKUP(MID(A47,1,7),#REF!,3,FALSE)) -> #REF! | H47: =+#REF! -> #REF! | I47: =+#REF! -> #REF! | J47: =+#REF! -> #REF! | K47: =+#REF! -> #REF! | M47: =+VACANTES!H60 -> 25 | N47: =+VACANTES!I60 -> 0 | O47: =+VACANTES!J60 -> 0 | P47: =+VACANTES!K60 -> 2 | Q47: =+VACANTES!L60 -> 3 | R47: =+VACANTES!N60 -> 30 | S47: =+R47-Q47 -> 27
A48: =+#REF! -> #REF! | B48: =+#REF! -> #REF! | C48: =+#REF! -> #REF! | D48: =+#REF! -> #REF! | E48: =+#REF! -> #REF! | F48: 5469598-5 | G48: =IF(D48="","",VLOOKUP(MID(A48,1,7),#REF!,3,FALSE)) -> #REF! | H48: =+#REF! -> #REF! | I48: =+#REF! -> #REF! | J48: =+#REF! -> #REF! | K48: =+#REF! -> #REF! | M48: =+VACANTES!#REF! -> #REF! | N48: =+VACANTES!#REF! -> #REF! | O48: =+VACANTES!#REF! -> #REF! | P48: =+VACANTES!#REF! -> #REF! | Q48: =+VACANTES!#REF! -> #REF! | R48: =+VACANTES!#REF! -> #REF! | S48: =+R48-Q48 -> #REF!
A49: =+#REF! -> #REF! | B49: =+#REF! -> #REF! | C49: =+#REF! -> #REF! | D49: =+#REF! -> #REF! | E49: =+#REF! -> #REF! | F49: 9757642-4 | G49: =IF(D49="","",VLOOKUP(MID(A49,1,7),#REF!,3,FALSE)) -> #REF! | H49: =+#REF! -> #REF! | I49: =+#REF! -> #REF! | J49: =+#REF! -> #REF! | K49: =+#REF! -> #REF! | M49: =+VACANTES!H61 -> 30 | N49: =+VACANTES!I61 -> 0 | O49: =+VACANTES!J61 -> 0 | P49: =+VACANTES!K61 -> 3 | Q49: =+VACANTES!L61 -> 2 | R49: =+VACANTES!N61 -> 35 | S49: =+R49-Q49 -> 33
A50: =+#REF! -> #REF! | B50: =+#REF! -> #REF! | C50: =+#REF! -> #REF! | D50: =+#REF! -> #REF! | E50: =+#REF! -> #REF! | F50: 7016179-6 | G50: =IF(D50="","",VLOOKUP(MID(A50,1,7),#REF!,3,FALSE)) -> #REF! | H50: =+#REF! -> #REF! | I50: =+#REF! -> #REF! | J50: =+#REF! -> #REF! | K50: =+#REF! -> #REF! | M50: =+VACANTES!#REF! -> #REF! | N50: =+VACANTES!#REF! -> #REF! | O50: =+VACANTES!#REF! -> #REF! | P50: =+VACANTES!#REF! -> #REF! | Q50: =+VACANTES!#REF! -> #REF! | R50: =+VACANTES!#REF! -> #REF! | S50: =+R50-Q50 -> #REF!
A51: =+#REF! -> #REF! | B51: =+#REF! -> #REF! | C51: =+#REF! -> #REF! | D51: =+#REF! -> #REF! | E51: =+#REF! -> #REF! | F51: 8882155-6 | G51: =IF(D51="","",VLOOKUP(MID(A51,1,7),#REF!,3,FALSE)) -> #REF! | H51: =+#REF! -> #REF! | I51: =+#REF! -> #REF! | J51: =+#REF! -> #REF! | K51: =+#REF! -> #REF! | M51: =+VACANTES!H62 -> 55 | N51: =+VACANTES!I62 -> 0 | O51: =+VACANTES!J62 -> 0 | P51: =+VACANTES!K62 -> 5 | Q51: =+VACANTES!L62 -> 5 | R51: =+VACANTES!N62 -> 65 | S51: =+R51-Q51 -> 60
A52: =+#REF! -> #REF! | B52: =+#REF! -> #REF! | C52: =+#REF! -> #REF! | D52: =+#REF! -> #REF! | E52: =+#REF! -> #REF! | F52: 5668399-2 | G52: =IF(D52="","",VLOOKUP(MID(A52,1,7),#REF!,3,FALSE)) -> #REF! | H52: =+#REF! -> #REF! | I52: =+#REF! -> #REF! | J52: =+#REF! -> #REF! | K52: =+#REF! -> #REF! | M52: =+VACANTES!H63 -> 20 | N52: =+VACANTES!I63 -> 0 | O52: =+VACANTES!J63 -> 0 | P52: =+VACANTES!K63 -> 5 | Q52: =+VACANTES!L63 -> 5 | R52: =+VACANTES!N63 -> 30 | S52: =+R52-Q52 -> 25
A53: =+#REF! -> #REF! | B53: =+#REF! -> #REF! | C53: =+#REF! -> #REF! | D53: =+#REF! -> #REF! | E53: N.N | G53: =IF(D53="","",VLOOKUP(MID(A53,1,7),#REF!,3,FALSE)) -> #REF! | H53: =+#REF! -> #REF! | I53: =+#REF! -> #REF! | J53: =+#REF! -> #REF! | K53: =+#REF! -> #REF! | M53: =+VACANTES!#REF! -> #REF! | N53: =+VACANTES!#REF! -> #REF! | O53: =+VACANTES!#REF! -> #REF! | P53: =+VACANTES!#REF! -> #REF! | Q53: =+VACANTES!#REF! -> #REF! | R53: =+VACANTES!#REF! -> #REF! | S53: =+R53-Q53 -> #REF!
A54: =+#REF! -> #REF! | B54: =+#REF! -> #REF! | C54: =+#REF! -> #REF! | D54: =+#REF! -> #REF! | E54: =+#REF! -> #REF! | F54: 10524744-3 | G54: =IF(D54="","",VLOOKUP(MID(A54,1,7),#REF!,3,FALSE)) -> #REF! | H54: =+#REF! -> #REF! | I54: =+#REF! -> #REF! | J54: =+#REF! -> #REF! | K54: =+#REF! -> #REF! | M54: =+VACANTES!H65 -> 60 | N54: =+VACANTES!I65 -> 0 | O54: =+VACANTES!J65 -> 0 | P54: =+VACANTES!K65 -> 3 | Q54: =+VACANTES!L65 -> 2 | R54: =+VACANTES!N65 -> 65 | S54: =+R54-Q54 -> 63
A55: =+#REF! -> #REF! | B55: =+#REF! -> #REF! | C55: =+#REF! -> #REF! | D55: =+#REF! -> #REF! | E55: =+#REF! -> #REF! | F55: 9572426-4 | G55: =IF(D55="","",VLOOKUP(MID(A55,1,7),#REF!,3,FALSE)) -> #REF! | H55: =+#REF! -> #REF! | I55: =+#REF! -> #REF! | J55: =+#REF! -> #REF! | K55: =+#REF! -> #REF! | M55: =+VACANTES!H67 -> 60 | N55: =+VACANTES!I67 -> 0 | O55: =+VACANTES!J67 -> 0 | P55: =+VACANTES!K67 -> 3 | Q55: =+VACANTES!L67 -> 2 | R55: =+VACANTES!N67 -> 65 | S55: =+R55-Q55 -> 63
A58: CURSOS MINIMOS INGENIERIA COMERCIAL | G58: =IF(D58="","",VLOOKUP(MID(A58,1,7),#REF!,3,FALSE))
A59: Sigla | B59: Sec. | C59: Créd. | D59: Nombre del Curso | E59: Prof. | G59: Requisitos | H59: Hor. | I59: Sala | J59: Hor. | K59: Sala | M59: =+VACANTES!H71 -> UA05 | N59: =+VACANTES!I71 -> UA11 | O59: =+VACANTES!J71 -> UA07 | P59: =+VACANTES!K71 -> FG | Q59: =+VACANTES!L71 -> INTERC. | R59: =+VACANTES!N71 -> TOTAL | S59: TOTAL
A60: =+#REF! -> #REF! | B60: =+#REF! -> #REF! | C60: =+#REF! -> #REF! | D60: =+#REF! -> #REF! | E60: =+#REF! -> #REF! | F60: 9719183-2 | G60: =IF(D60="","",VLOOKUP(MID(A60,1,7),#REF!,3,FALSE)) -> #REF! | H60: =+#REF! -> #REF! | I60: =+#REF! -> #REF! | J60: =+#REF! -> #REF! | K60: =+#REF! -> #REF! | M60: =+VACANTES!H72 -> 50 | N60: =+VACANTES!I72 -> 0 | O60: =+VACANTES!J72 -> 0 | P60: =+VACANTES!K72 -> 0 | Q60: =+VACANTES!L72 -> 0 | R60: =+VACANTES!N72 -> 50 | S60: =+R60-Q60 -> 50
A61: =+#REF! -> #REF! | B61: =+#REF! -> #REF! | C61: =+#REF! -> #REF! | D61: =+#REF! -> #REF! | E61: =+#REF! -> #REF! | F61: 8860493-8 | G61: =IF(D61="","",VLOOKUP(MID(A61,1,7),#REF!,3,FALSE)) -> #REF! | H61: =+#REF! -> #REF! | I61: =+#REF! -> #REF! | J61: =+#REF! -> #REF! | K61: =+#REF! -> #REF! | M61: =+VACANTES!H73 -> 50 | N61: =+VACANTES!I73 -> 0 | O61: =+VACANTES!J73 -> 0 | P61: =+VACANTES!K73 -> 0 | Q61: =+VACANTES!L73 -> 0 | R61: =+VACANTES!N73 -> 50 | S61: =+R61-Q61 -> 50
A62: =+#REF! -> #REF! | B62: =+#REF! -> #REF! | C62: =+#REF! -> #REF! | D62: =+#REF! -> #REF! | E62: =+#REF! -> #REF! | F62: 9128578-9 | G62: =IF(D62="","",VLOOKUP(MID(A62,1,7),#REF!,3,FALSE)) -> #REF! | H62: =+#REF! -> #REF! | I62: =+#REF! -> #REF! | J62: =+#REF! -> #REF! | K62: =+#REF! -> #REF! | M62: =+VACANTES!H74 -> 35 | N62: =+VACANTES!I74 -> 0 | O62: =+VACANTES!J74 -> 0 | P62: =+VACANTES!K74 -> 0 | Q62: =+VACANTES!L74 -> 0 | R62: =+VACANTES!N74 -> 35 | S62: =+R62-Q62 -> 35
A63: =+#REF! -> #REF! | B63: =+#REF! -> #REF! | C63: =+#REF! -> #REF! | D63: =+#REF! -> #REF! | E63: =+#REF! -> #REF! | F63: =+F62 -> 9128578-9 | G63: =IF(D63="","",VLOOKUP(MID(A63,1,7),#REF!,3,FALSE)) -> #REF! | H63: =+#REF! -> #REF! | I63: =+#REF! -> #REF! | J63: =+#REF! -> #REF! | K63: =+#REF! -> #REF! | M63: =+VACANTES!H75 -> 35 | N63: =+VACANTES!I75 -> 0 | O63: =+VACANTES!J75 -> 0 | P63: =+VACANTES!K75 -> 0 | Q63: =+VACANTES!L75 -> 0 | R63: =+VACANTES!N75 -> 35 | S63: =+R63-Q63 -> 35
A64: =+#REF! -> #REF! | B64: =+#REF! -> #REF! | C64: =+#REF! -> #REF! | D64: =+#REF! -> #REF! | E64: =+#REF! -> #REF! | F64: 8956105-1 | G64: =IF(D64="","",VLOOKUP(MID(A64,1,7),#REF!,3,FALSE)) -> #REF! | H64: =+#REF! -> #REF! | I64: =+#REF! -> #REF! | J64: =+#REF! -> #REF! | K64: =+#REF! -> #REF! | M64: =+VACANTES!H76 -> 35 | N64: =+VACANTES!I76 -> 0 | O64: =+VACANTES!J76 -> 0 | P64: =+VACANTES!K76 -> 0 | Q64: =+VACANTES!L76 -> 0 | R64: =+VACANTES!N76 -> 35 | S64: =+R64-Q64 -> 35
A65: =+#REF! -> #REF! | B65: =+#REF! -> #REF! | C65: =+#REF! -> #REF! | D65: =+#REF! -> #REF! | E65: =+#REF! -> #REF! | F65: 7129878-7 | G65: =IF(D65="","",VLOOKUP(MID(A65,1,7),#REF!,3,FALSE)) -> #REF! | H65: =+#REF! -> #REF! | I65: =+#REF! -> #REF! | J65: =+#REF! -> #REF! | K65: =+#REF! -> #REF! | M65: =+VACANTES!H77 -> 60 | N65: =+VACANTES!I77 -> 0 | O65: =+VACANTES!J77 -> 0 | P65: =+VACANTES!K77 -> 5 | Q65: =+VACANTES!L77 -> 0 | R65: =+VACANTES!N77 -> 65 | S65: =+R65-Q65 -> 65
A66: =+#REF! -> #REF! | B66: =+#REF! -> #REF! | C66: =+#REF! -> #REF! | D66: =+#REF! -> #REF! | E66: =+#REF! -> #REF! | F66: 12721018-7 | G66: =IF(D66="","",VLOOKUP(MID(A66,1,7),#REF!,3,FALSE)) -> #REF! | H66: =+#REF! -> #REF! | I66: =+#REF! -> #REF! | J66: =+#REF! -> #REF! | K66: =+#REF! -> #REF! | M66: =+VACANTES!H78 -> 60 | N66: =+VACANTES!I78 -> 0 | O66: =+VACANTES!J78 -> 0 | P66: =+VACANTES!K78 -> 5 | Q66: =+VACANTES!L78 -> 0 | R66: =+VACANTES!N78 -> 65 | S66: =+R66-Q66 -> 65
A67: =+#REF! -> #REF! | B67: =+#REF! -> #REF! | C67: =+#REF! -> #REF! | D67: =+#REF! -> #REF! | E67: =+#REF! -> #REF! | F67: 7044604-9 | G67: =IF(D67="","",VLOOKUP(MID(A67,1,7),#REF!,3,FALSE)) -> #REF! | H67: =+#REF! -> #REF! | I67: =+#REF! -> #REF! | J67: =+#REF! -> #REF! | K67: =+#REF! -> #REF! | M67: =+VACANTES!H79 -> 60 | N67: =+VACANTES!I79 -> 0 | O67: =+VACANTES!J79 -> 0 | P67: =+VACANTES!K79 -> 0 | Q67: =+VACANTES!L79 -> 0 | R67: =+VACANTES!N79 -> 60 | S67: =+R67-Q67 -> 60
A68: =+#REF! -> #REF! | B68: =+#REF! -> #REF! | C68: =+#REF! -> #REF! | D68: =+#REF! -> #REF! | E68: =+#REF! -> #REF! | F68: 5668399-2 | G68: =IF(D68="","",VLOOKUP(MID(A68,1,7),#REF!,3,FALSE)) -> #REF! | H68: =+#REF! -> #REF! | I68: =+#REF! -> #REF! | J68: =+#REF! -> #REF! | K68: =+#REF! -> #REF! | M68: =+VACANTES!H80 -> 60 | N68: =+VACANTES!I80 -> 0 | O68: =+VACANTES!J80 -> 0 | P68: =+VACANTES!K80 -> 0 | Q68: =+VACANTES!L80 -> 0 | R68: =+VACANTES!N80 -> 60 | S68: =+R68-Q68 -> 60
D70: =IF(A70="","",VLOOKUP(MID(A70,1,7),#REF!,2,FALSE)) | G70: =IF(D70="","",VLOOKUP(MID(A70,1,7),#REF!,3,FALSE))
A71: CURSOS OPTATIVOS INGENIERIA COMERCIAL | G71: =IF(D71="","",VLOOKUP(MID(A71,1,7),#REF!,3,FALSE))
A72: Sigla | B72: Sec. | C72: Créd. | D72: Nombre del Curso | E72: Prof. | G72: Requisitos | H72: Hor. | I72: Sala | J72: Hor. | K72: Sala | M72: =+VACANTES!H84 -> UA05 | N72: =+VACANTES!I84 -> UA11 | O72: =+VACANTES!J84 -> UA07 | P72: =+VACANTES!K84 -> FG | Q72: =+VACANTES!L84 -> INTERC. | R72: =+VACANTES!N84 -> TOTAL | S72: TOTAL
A73: =+#REF! -> #REF! | B73: =+#REF! -> #REF! | C73: =+#REF! -> #REF! | D73: =+#REF! -> #REF! | E73: =+#REF! -> #REF! | F73: 8361980-5 | G73: =IF(D73="","",VLOOKUP(MID(A73,1,7),#REF!,3,FALSE)) -> #REF! | H73: =+#REF! -> #REF! | I73: =+#REF! -> #REF! | J73: =+#REF! -> #REF! | K73: =+#REF! -> #REF! | M73: =+VACANTES!H85 -> 60 | N73: =+VACANTES!I85 -> 0 | O73: =+VACANTES!J85 -> 0 | P73: =+VACANTES!K85 -> 3 | Q73: =+VACANTES!L85 -> 0 | R73: =+VACANTES!N85 -> 63 | S73: =+R73-Q73 -> 63
A74: =+#REF! -> #REF! | B74: =+#REF! -> #REF! | C74: =+#REF! -> #REF! | D74: =+#REF! -> #REF! | E74: =+#REF! -> #REF! | F74: 7081424-2 | G74: =IF(D74="","",VLOOKUP(MID(A74,1,7),#REF!,3,FALSE)) -> #REF! | H74: =+#REF! -> #REF! | I74: =+#REF! -> #REF! | J74: =+#REF! -> #REF! | K74: =+#REF! -> #REF! | M74: =+VACANTES!H86 -> 35 | N74: =+VACANTES!I86 -> 0 | O74: =+VACANTES!J86 -> 0 | P74: =+VACANTES!K86 -> 5 | Q74: =+VACANTES!L86 -> 0 | R74: =+VACANTES!N86 -> 40 | S74: =+R74-Q74 -> 40
A75: =+#REF! -> #REF! | B75: =+#REF! -> #REF! | C75: =+#REF! -> #REF! | D75: =+#REF! -> #REF! | E75: =+#REF! -> #REF! | F75: 9977192-5 | G75: =IF(D75="","",VLOOKUP(MID(A75,1,7),#REF!,3,FALSE)) -> #REF! | H75: =+#REF! -> #REF! | I75: =+#REF! -> #REF! | J75: =+#REF! -> #REF! | K75: =+#REF! -> #REF! | M75: =+VACANTES!H87 -> 28 | N75: =+VACANTES!I87 -> 0 | O75: =+VACANTES!J87 -> 0 | P75: =+VACANTES!K87 -> 2 | Q75: =+VACANTES!L87 -> 0 | R75: =+VACANTES!N87 -> 30 | S75: =+R75-Q75 -> 30
A76: =+#REF! -> #REF! | B76: =+#REF! -> #REF! | C76: =+#REF! -> #REF! | D76: =+#REF! -> #REF! | E76: =+#REF! -> #REF! | F76: =+F65 -> 7129878-7 | G76: =IF(D76="","",VLOOKUP(MID(A76,1,7),#REF!,3,FALSE)) -> #REF! | H76: =+#REF! -> #REF! | I76: =+#REF! -> #REF! | J76: =+#REF! -> #REF! | K76: =+#REF! -> #REF! | M76: =+VACANTES!H88 -> 60 | N76: =+VACANTES!I88 -> 0 | O76: =+VACANTES!J88 -> 0 | P76: =+VACANTES!K88 -> 5 | Q76: =+VACANTES!L88 -> 0 | R76: =+VACANTES!N88 -> 65 | S76: =+R76-Q76 -> 65
A77: =+#REF! -> #REF! | B77: =+#REF! -> #REF! | C77: =+#REF! -> #REF! | D77: =+#REF! -> #REF! | E77: =+#REF! -> #REF! | F77: 6910146-1 | G77: =IF(D77="","",VLOOKUP(MID(A77,1,7),#REF!,3,FALSE)) -> #REF! | H77: =+#REF! -> #REF! | I77: =+#REF! -> #REF! | J77: =+#REF! -> #REF! | K77: =+#REF! -> #REF! | M77: =+VACANTES!H89 -> 60 | N77: =+VACANTES!I89 -> 0 | O77: =+VACANTES!J89 -> 0 | P77: =+VACANTES!K89 -> 5 | Q77: =+VACANTES!L89 -> 10 | R77: =+VACANTES!N89 -> 75 | S77: =+R77-Q77 -> 65
A78: =+#REF! -> #REF! | B78: =+#REF! -> #REF! | C78: =+#REF! -> #REF! | D78: =+#REF! -> #REF! | E78: =+#REF! -> #REF! | F78: 6693685-6 | G78: =IF(D78="","",VLOOKUP(MID(A78,1,7),#REF!,3,FALSE)) -> #REF! | H78: =+#REF! -> #REF! | I78: =+#REF! -> #REF! | J78: =+#REF! -> #REF! | K78: =+#REF! -> #REF! | M78: =+VACANTES!H90 -> 60 | N78: =+VACANTES!I90 -> 0 | O78: =+VACANTES!J90 -> 0 | P78: =+VACANTES!K90 -> 3 | Q78: =+VACANTES!L90 -> 2 | R78: =+VACANTES!N90 -> 65 | S78: =+R78-Q78 -> 63
A79: =+#REF! -> #REF! | B79: =+#REF! -> #REF! | C79: =+#REF! -> #REF! | D79: =+#REF! -> #REF! | E79: =+#REF! -> #REF! | F79: 10622139-1 | G79: =IF(D79="","",VLOOKUP(MID(A79,1,7),#REF!,3,FALSE)) -> #REF! | H79: =+#REF! -> #REF! | I79: =+#REF! -> #REF! | J79: =+#REF! -> #REF! | K79: =+#REF! -> #REF! | M79: =+VACANTES!H91 -> 55 | N79: =+VACANTES!I91 -> 0 | O79: =+VACANTES!J91 -> 0 | P79: =+VACANTES!K91 -> 3 | Q79: =+VACANTES!L91 -> 2 | R79: =+VACANTES!N91 -> 60 | S79: =+R79-Q79 -> 58
A80: =+#REF! -> #REF! | B80: =+#REF! -> #REF! | C80: =+#REF! -> #REF! | D80: =+#REF! -> #REF! | E80: N.N | G80: =IF(D80="","",VLOOKUP(MID(A80,1,7),#REF!,3,FALSE)) -> #REF! | H80: =+#REF! -> #REF! | I80: =+#REF! -> #REF! | J80: =+#REF! -> #REF! | K80: =+#REF! -> #REF! | M80: =+VACANTES!H92 -> 60 | N80: =+VACANTES!I92 -> 0 | O80: =+VACANTES!J92 -> 0 | P80: =+VACANTES!K92 -> 3 | Q80: =+VACANTES!L92 -> 2 | R80: =+VACANTES!N92 -> 65 | S80: =+R80-Q80 -> 63
A81: =+#REF! -> #REF! | B81: =+#REF! -> #REF! | C81: =+#REF! -> #REF! | D81: =+#REF! -> #REF! | E81: =+#REF! -> #REF! | F81: 6948688-6 | G81: =IF(D81="","",VLOOKUP(MID(A81,1,7),#REF!,3,FALSE)) -> #REF! | H81: =+#REF! -> #REF! | I81: =+#REF! -> #REF! | J81: =+#REF! -> #REF! | K81: =+#REF! -> #REF! | M81: =+VACANTES!H93 -> 60 | N81: =+VACANTES!I93 -> 0 | O81: =+VACANTES!J93 -> 0 | P81: =+VACANTES!K93 -> 3 | Q81: =+VACANTES!L93 -> 2 | R81: =+VACANTES!N93 -> 65 | S81: =+R81-Q81 -> 63
A83: CURSOS DE SERVICIO | G83: =IF(D83="","",VLOOKUP(MID(A83,1,7),#REF!,3,FALSE))
A84: Sigla | B84: Sec. | C84: Créd. | D84: Nombre del Curso | E84: Prof. | G84: Requisitos | H84: Hor. | I84: Sala | J84: Hor. | K84: Sala | M84: =+VACANTES!I96 -> UA01 | N84: =+VACANTES!J96 -> UA10 | O84: =+VACANTES!K96 -> FG | P84: TOTAL | Q84: =+VACANTES!N96 -> TOTAL
A85: =+#REF! -> #REF! | B85: =+#REF! -> #REF! | C85: =+#REF! -> #REF! | D85: =+#REF! -> #REF! | E85: NN | G85: CCL2264 | H85: =+#REF! -> #REF! | I85: =+#REF! -> #REF! | J85: =+#REF! -> #REF! | K85: =+#REF! -> #REF! | M85: =+VACANTES!I97 -> 50 | N85: =+VACANTES!J97 -> 4 | O85: =+VACANTES!K97 -> 4 | P85: =SUM(M85:O85) -> 58 | Q85: =+VACANTES!N97 -> 60
A86: =+#REF! -> #REF! | B86: =+#REF! -> #REF! | C86: =+#REF! -> #REF! | D86: =+#REF! -> #REF! | E86: N.N | G86: CCL2265 | H86: =+#REF! -> #REF! | I86: =+#REF! -> #REF! | J86: =+#REF! -> #REF! | K86: =+#REF! -> #REF! | M86: =+VACANTES!I98 -> 50 | N86: =+VACANTES!J98 -> 4 | O86: =+VACANTES!K98 -> 4 | P86: =SUM(M86:O86) -> 58 | Q86: =+VACANTES!N98 -> 60
A87: =+#REF! -> #REF! | B87: =+#REF! -> #REF! | C87: =+#REF! -> #REF! | D87: =+#REF! -> #REF! | E87: =+#REF! -> #REF! | G87: =IF(D87="","",VLOOKUP(MID(A87,1,7),#REF!,3,FALSE)) -> #REF! | H87: =+#REF! -> #REF! | I87: =+#REF! -> #REF! | J87: =+#REF! -> #REF! | K87: =+#REF! -> #REF! | M87: =+VACANTES!I99 -> 20 | N87: =+VACANTES!J99 -> 0 | O87: =+VACANTES!K99 -> 5 | P87: =SUM(M87:O87) -> 25 | Q87: =+VACANTES!N99 -> 30
A88: =+#REF! -> #REF! | B88: =+#REF! -> #REF! | C88: =+#REF! -> #REF! | D88: =+#REF! -> #REF! | E88: =+#REF! -> #REF! | G88: =IF(D88="","",VLOOKUP(MID(A88,1,7),#REF!,3,FALSE)) -> #REF! | H88: =+#REF! -> #REF! | I88: =+#REF! -> #REF! | J88: =+#REF! -> #REF! | K88: =+#REF! -> #REF! | M88: =+VACANTES!I101 -> 0 | N88: =+VACANTES!J101 -> 0 | O88: =+VACANTES!K101 -> 0 | P88: =SUM(M88:O88) -> 0 | Q88: =+VACANTES!N101 -> 0
E91: PONTIFICIA UNIVERSIDAD CATOLICA DE CHILE
E92: INSTITUTO DE ECONOMIA
E93: PROGRAMACIÓN DE CURSOS PRIMER SEMESTRE DEL 2006
G94: =IF(D94="","",VLOOKUP(MID(A94,1,7),#REF!,3,FALSE))
G95: =IF(D95="","",VLOOKUP(MID(A95,1,7),#REF!,3,FALSE))
A96: CURSOS MINIMOS LICENCIATURA | G96: =IF(D96="","",VLOOKUP(MID(A96,1,7),#REF!,3,FALSE))
G97: =IF(D97="","",VLOOKUP(MID(A97,1,7),#REF!,3,FALSE)) | H97: Clases | J97: Ayudantía
A98: Sigla | B98: Sec. | C98: Créd | D98: Nombre del curso | E98: Prof | G98: Requisitos | H98: Hor. | I98: Sala | J98: Hor. | K98: Sala | M98: =+VACANTES!H105 -> UA05 | N98: =+VACANTES!I105 -> UA11 | O98: =+VACANTES!J105 -> UA07 | P98: =+VACANTES!K105 -> FG | Q98: =+VACANTES!L105 -> INTERC. | R98: =+VACANTES!N105 -> TOTAL | S98: TOTAL
A99: =+#REF! -> #REF! | B99: =+#REF! -> #REF! | C99: =+#REF! -> #REF! | D99: =+#REF! -> #REF! | E99: =+#REF! -> #REF! | F99: 8609956-K | G99: =IF(D99="","",VLOOKUP(MID(A99,1,7),#REF!,3,FALSE)) -> #REF! | H99: =+#REF! -> #REF! | I99: =+#REF! -> #REF! | J99: =+#REF! -> #REF! | K99: =+#REF! -> #REF! | M99: =+VACANTES!H106 -> 60 | N99: =+VACANTES!I106 -> 0 | O99: =+VACANTES!J106 -> 0 | P99: =+VACANTES!K106 -> 10 | Q99: =+VACANTES!L106 -> 5 | R99: =+VACANTES!N106 -> 75 | S99: =+R99-Q99 -> 70
A100: =+#REF! -> #REF! | B100: =+#REF! -> #REF! | C100: =+#REF! -> #REF! | D100: =+#REF! -> #REF! | E100: =+#REF! -> #REF! | F100: =+F101 -> 2929447-K | G100: =IF(D100="","",VLOOKUP(MID(A100,1,7),#REF!,3,FALSE)) -> #REF! | H100: =+#REF! -> #REF! | I100: =+#REF! -> #REF! | J100: =+#REF! -> #REF! | K100: =+#REF! -> #REF! | M100: =+VACANTES!H107 -> 55 | N100: =+VACANTES!I107 -> 6 | O100: =+VACANTES!J107 -> 11 | P100: =+VACANTES!K107 -> 4 | Q100: =+VACANTES!L107 -> 2 | R100: =+VACANTES!N107 -> 78 | S100: =+R100-Q100 -> 76
A101: =+#REF! -> #REF! | B101: =+#REF! -> #REF! | C101: =+#REF! -> #REF! | D101: =+#REF! -> #REF! | E101: =+#REF! -> #REF! | F101: 2929447-K | G101: =IF(D101="","",VLOOKUP(MID(A101,1,7),#REF!,3,FALSE)) -> #REF! | H101: =+#REF! -> #REF! | I101: =+#REF! -> #REF! | J101: =+#REF! -> #REF! | K101: =+#REF! -> #REF! | M101: =+VACANTES!H108 -> 55 | N101: =+VACANTES!I108 -> 6 | O101: =+VACANTES!J108 -> 11 | P101: =+VACANTES!K108 -> 4 | Q101: =+VACANTES!L108 -> 2 | R101: =+VACANTES!N108 -> 78 | S101: =+R101-Q101 -> 76
A102: =+#REF! -> #REF! | B102: =+#REF! -> #REF! | C102: =+#REF! -> #REF! | D102: =+#REF! -> #REF! | E102: =+#REF! -> #REF! | F102: 6379928-9 | G102: =IF(D101="","",VLOOKUP(MID(A101,1,7),#REF!,3,FALSE)) -> #REF! | H102: =+#REF! -> #REF! | I102: =+#REF! -> #REF! | J102: =+#REF! -> #REF! | K102: =+#REF! -> #REF! | M102: =+VACANTES!H109 -> 55 | N102: =+VACANTES!I109 -> 6 | O102: =+VACANTES!J109 -> 11 | P102: =+VACANTES!K109 -> 4 | Q102: =+VACANTES!L109 -> 2 | R102: =+VACANTES!N109 -> 78 | S102: =+R102-Q102 -> 76
A103: =+#REF! -> #REF! | B103: =+#REF! -> #REF! | C103: =+#REF! -> #REF! | D103: =+#REF! -> #REF! | E103: =+#REF! -> #REF! | F103: 7107215-0 | G103: =IF(D102="","",VLOOKUP(MID(A102,1,7),#REF!,3,FALSE)) -> #REF! | H103: =+#REF! -> #REF! | I103: =+#REF! -> #REF! | J103: =+#REF! -> #REF! | K103: =+#REF! -> #REF! | M103: =+VACANTES!H110 -> 55 | N103: =+VACANTES!I110 -> 6 | O103: =+VACANTES!J110 -> 11 | P103: =+VACANTES!K110 -> 4 | Q103: =+VACANTES!L110 -> 2 | R103: =+VACANTES!N110 -> 78 | S103: =+R103-Q103 -> 76
A104: =+#REF! -> #REF! | B104: =+#REF! -> #REF! | C104: =+#REF! -> #REF! | D104: =+#REF! -> #REF! | E104: =+#REF! -> #REF! | F104: 13550375-4 | G104: =IF(D104="","",VLOOKUP(MID(A104,1,7),#REF!,3,FALSE)) -> #REF! | H104: =+#REF! -> #REF! | I104: =+#REF! -> #REF! | J104: =+#REF! -> #REF! | K104: =+#REF! -> #REF! | M104: =+VACANTES!H111 -> 55 | N104: =+VACANTES!I111 -> 6 | O104: =+VACANTES!J111 -> 11 | P104: =+VACANTES!K111 -> 4 | Q104: =+VACANTES!L111 -> 2 | R104: =+VACANTES!N111 -> 78 | S104: =+R104-Q104 -> 76
A105: =+#REF! -> #REF! | B105: =+#REF! -> #REF! | C105: =+#REF! -> #REF! | D105: =+#REF! -> #REF! | E105: =+#REF! -> #REF! | F105: 21619704-6 | G105: =IF(D105="","",VLOOKUP(MID(A105,1,7),#REF!,3,FALSE)) -> #REF! | H105: =+#REF! -> #REF! | I105: =+#REF! -> #REF! | J105: =+#REF! -> #REF! | K105: =+#REF! -> #REF! | M105: =+VACANTES!H112 -> 45 | N105: =+VACANTES!I112 -> 10 | O105: =+VACANTES!J112 -> 15 | P105: =+VACANTES!K112 -> 3 | Q105: =+VACANTES!L112 -> 2 | R105: =+VACANTES!N112 -> 80 | S105: =+R105-Q105 -> 78
A106: =+#REF! -> #REF! | B106: =+#REF! -> #REF! | C106: =+#REF! -> #REF! | D106: =+#REF! -> #REF! | E106: =+#REF! -> #REF! | F106: 8662300-5 | G106: =IF(D106="","",VLOOKUP(MID(A106,1,7),#REF!,3,FALSE)) -> #REF! | H106: =+#REF! -> #REF! | I106: =+#REF! -> #REF! | J106: =+#REF! -> #REF! | K106: =+#REF! -> #REF! | M106: =+VACANTES!H113 -> 45 | N106: =+VACANTES!I113 -> 10 | O106: =+VACANTES!J113 -> 15 | P106: =+VACANTES!K113 -> 3 | Q106: =+VACANTES!L113 -> 2 | R106: =+VACANTES!N113 -> 80 | S106: =+R106-Q106 -> 78
A107: =+#REF! -> #REF! | B107: =+#REF! -> #REF! | C107: =+#REF! -> #REF! | D107: =+#REF! -> #REF! | E107: =+#REF! -> #REF! | F107: 6344937-7 | G107: =IF(D107="","",VLOOKUP(MID(A107,1,7),#REF!,3,FALSE)) -> #REF! | H107: =+#REF! -> #REF! | I107: =+#REF! -> #REF! | J107: =+#REF! -> #REF! | K107: =+#REF! -> #REF! | M107: =+VACANTES!H114 -> 55 | N107: =+VACANTES!I114 -> 0 | O107: =+VACANTES!J114 -> 0 | P107: =+VACANTES!K114 -> 5 | Q107: =+VACANTES!L114 -> 0 | R107: =+VACANTES!N114 -> 60 | S107: =+R107-Q107 -> 60
A108: =+#REF! -> #REF! | B108: =+#REF! -> #REF! | C108: =+#REF! -> #REF! | D108: =+#REF! -> #REF! | E108: =+#REF! -> #REF! | F108: 21897198-9 | G108: =IF(D108="","",VLOOKUP(MID(A108,1,7),#REF!,3,FALSE)) -> #REF! | H108: =+#REF! -> #REF! | I108: =+#REF! -> #REF! | J108: =+#REF! -> #REF! | K108: =+#REF! -> #REF! | M108: =+VACANTES!H115 -> 55 | N108: =+VACANTES!I115 -> 0 | O108: =+VACANTES!J115 -> 0 | P108: =+VACANTES!K115 -> 5 | Q108: =+VACANTES!L115 -> 0 | R108: =+VACANTES!N115 -> 60 | S108: =+R108-Q108 -> 60
A109: =+#REF! -> #REF! | B109: =+#REF! -> #REF! | C109: =+#REF! -> #REF! | D109: =+#REF! -> #REF! | E109: =+#REF! -> #REF! | F109: 12645487-2 | G109: =IF(D109="","",VLOOKUP(MID(A109,1,7),#REF!,3,FALSE)) -> #REF! | H109: =+#REF! -> #REF! | I109: =+#REF! -> #REF! | J109: =+#REF! -> #REF! | K109: =+#REF! -> #REF! | M109: =+VACANTES!H116 -> 55 | N109: =+VACANTES!I116 -> 0 | O109: =+VACANTES!J116 -> 0 | P109: =+VACANTES!K116 -> 5 | Q109: =+VACANTES!L116 -> 0 | R109: =+VACANTES!N116 -> 60 | S109: =+R109-Q109 -> 60
...
